{
  "data": [
    {
      "hoverinfo": "none",
      "line": {
        "color": "#ff6f6f ",
        "shape": "linear",
        "width": 3.0
      },
      "mode": "lines",
      "textposition": "middle center",
      "type": "scatter",
      "x": [
        -0.852778,
        -0.637271
      ],
      "y": [
        0.440177,
        0.736826
      ]
    },
    {
      "hoverinfo": "none",
      "line": {
        "color": "#ff6f6f ",
        "shape": "linear",
        "width": 3.0
      },
      "mode": "lines",
      "textposition": "middle center",
      "type": "scatter",
      "x": [
        -0.637271,
        -0.852778
      ],
      "y": [
        0.736826,
        0.440177
      ]
    },
    {
      "hoverinfo": "none",
      "line": {
        "color": "#ff6f6f ",
        "shape": "linear",
        "width": 2.0
      },
      "mode": "lines",
      "textposition": "middle center",
      "type": "scatter",
      "x": [
        -0.852778,
        1.0
      ],
      "y": [
        0.440177,
        -0.026633
      ]
    },
    {
      "hoverinfo": "none",
      "line": {
        "color": "#ff6f6f ",
        "shape": "linear",
        "width": 2.0
      },
      "mode": "lines",
      "textposition": "middle center",
      "type": "scatter",
      "x": [
        1.0,
        -0.852778
      ],
      "y": [
        -0.026633,
        0.440177
      ]
    },
    {
      "hoverinfo": "none",
      "line": {
        "color": "#ff6f6f ",
        "shape": "linear",
        "width": 2.0
      },
      "mode": "lines",
      "textposition": "middle center",
      "type": "scatter",
      "x": [
        -0.852778,
        -0.542011
      ],
      "y": [
        0.440177,
        -0.741446
      ]
    },
    {
      "hoverinfo": "none",
      "line": {
        "color": "#ff6f6f ",
        "shape": "linear",
        "width": 2.0
      },
      "mode": "lines",
      "textposition": "middle center",
      "type": "scatter",
      "x": [
        -0.542011,
        -0.852778
      ],
      "y": [
        -0.741446,
        0.440177
      ]
    },
    {
      "hoverinfo": "none",
      "line": {
        "color": "#ff6f6f ",
        "shape": "linear",
        "width": 2.0
      },
      "mode": "lines",
      "textposition": "middle center",
      "type": "scatter",
      "x": [
        -0.920991,
        0.895121
      ],
      "y": [
        -0.258648,
        0.609387
      ]
    },
    {
      "hoverinfo": "none",
      "line": {
        "color": "#ff6f6f ",
        "shape": "linear",
        "width": 2.0
      },
      "mode": "lines",
      "textposition": "middle center",
      "type": "scatter",
      "x": [
        0.895121,
        -0.920991
      ],
      "y": [
        0.609387,
        -0.258648
      ]
    },
    {
      "hoverinfo": "none",
      "line": {
        "color": "#ff6f6f ",
        "shape": "linear",
        "width": 5.0
      },
      "mode": "lines",
      "textposition": "middle center",
      "type": "scatter",
      "x": [
        -0.920991,
        -0.542011
      ],
      "y": [
        -0.258648,
        -0.741446
      ]
    },
    {
      "hoverinfo": "none",
      "line": {
        "color": "#ff6f6f ",
        "shape": "linear",
        "width": 5.0
      },
      "mode": "lines",
      "textposition": "middle center",
      "type": "scatter",
      "x": [
        -0.542011,
        -0.920991
      ],
      "y": [
        -0.741446,
        -0.258648
      ]
    },
    {
      "hoverinfo": "none",
      "line": {
        "color": "#ff6f6f ",
        "shape": "linear",
        "width": 3.0
      },
      "mode": "lines",
      "textposition": "middle center",
      "type": "scatter",
      "x": [
        -0.920991,
        -0.10373
      ],
      "y": [
        -0.258648,
        0.787515
      ]
    },
    {
      "hoverinfo": "none",
      "line": {
        "color": "#ff6f6f ",
        "shape": "linear",
        "width": 3.0
      },
      "mode": "lines",
      "textposition": "middle center",
      "type": "scatter",
      "x": [
        -0.10373,
        -0.920991
      ],
      "y": [
        0.787515,
        -0.258648
      ]
    },
    {
      "hoverinfo": "none",
      "line": {
        "color": "#ff6f6f ",
        "shape": "linear",
        "width": 2.0
      },
      "mode": "lines",
      "textposition": "middle center",
      "type": "scatter",
      "x": [
        -0.637271,
        -0.679827
      ],
      "y": [
        0.736826,
        0.169582
      ]
    },
    {
      "hoverinfo": "none",
      "line": {
        "color": "#ff6f6f ",
        "shape": "linear",
        "width": 2.0
      },
      "mode": "lines",
      "textposition": "middle center",
      "type": "scatter",
      "x": [
        -0.679827,
        -0.637271
      ],
      "y": [
        0.169582,
        0.736826
      ]
    },
    {
      "hoverinfo": "none",
      "line": {
        "color": "#ff6f6f ",
        "shape": "linear",
        "width": 2.0
      },
      "mode": "lines",
      "textposition": "middle center",
      "type": "scatter",
      "x": [
        -0.992282,
        0.238369
      ],
      "y": [
        0.076038,
        0.989267
      ]
    },
    {
      "hoverinfo": "none",
      "line": {
        "color": "#ff6f6f ",
        "shape": "linear",
        "width": 2.0
      },
      "mode": "lines",
      "textposition": "middle center",
      "type": "scatter",
      "x": [
        0.238369,
        -0.992282
      ],
      "y": [
        0.989267,
        0.076038
      ]
    },
    {
      "hoverinfo": "none",
      "line": {
        "color": "#ff6f6f ",
        "shape": "linear",
        "width": 2.0
      },
      "mode": "lines",
      "textposition": "middle center",
      "type": "scatter",
      "x": [
        -0.992282,
        -0.303382
      ],
      "y": [
        0.076038,
        -0.967419
      ]
    },
    {
      "hoverinfo": "none",
      "line": {
        "color": "#ff6f6f ",
        "shape": "linear",
        "width": 2.0
      },
      "mode": "lines",
      "textposition": "middle center",
      "type": "scatter",
      "x": [
        -0.303382,
        -0.992282
      ],
      "y": [
        -0.967419,
        0.076038
      ]
    },
    {
      "hoverinfo": "none",
      "line": {
        "color": "#ff6f6f ",
        "shape": "linear",
        "width": 3.0
      },
      "mode": "lines",
      "textposition": "middle center",
      "type": "scatter",
      "x": [
        -0.992282,
        -0.10373
      ],
      "y": [
        0.076038,
        0.787515
      ]
    },
    {
      "hoverinfo": "none",
      "line": {
        "color": "#ff6f6f ",
        "shape": "linear",
        "width": 3.0
      },
      "mode": "lines",
      "textposition": "middle center",
      "type": "scatter",
      "x": [
        -0.10373,
        -0.992282
      ],
      "y": [
        0.787515,
        0.076038
      ]
    },
    {
      "hoverinfo": "none",
      "line": {
        "color": "#ff6f6f ",
        "shape": "linear",
        "width": 2.0
      },
      "mode": "lines",
      "textposition": "middle center",
      "type": "scatter",
      "x": [
        0.895121,
        0.238369
      ],
      "y": [
        0.609387,
        0.989267
      ]
    },
    {
      "hoverinfo": "none",
      "line": {
        "color": "#ff6f6f ",
        "shape": "linear",
        "width": 2.0
      },
      "mode": "lines",
      "textposition": "middle center",
      "type": "scatter",
      "x": [
        0.238369,
        0.895121
      ],
      "y": [
        0.989267,
        0.609387
      ]
    },
    {
      "hoverinfo": "none",
      "line": {
        "color": "#ff6f6f ",
        "shape": "linear",
        "width": 2.0
      },
      "mode": "lines",
      "textposition": "middle center",
      "type": "scatter",
      "x": [
        0.895121,
        0.926226
      ],
      "y": [
        0.609387,
        0.301567
      ]
    },
    {
      "hoverinfo": "none",
      "line": {
        "color": "#ff6f6f ",
        "shape": "linear",
        "width": 2.0
      },
      "mode": "lines",
      "textposition": "middle center",
      "type": "scatter",
      "x": [
        0.926226,
        0.895121
      ],
      "y": [
        0.301567,
        0.609387
      ]
    },
    {
      "hoverinfo": "none",
      "line": {
        "color": "#ff6f6f ",
        "shape": "linear",
        "width": 3.0
      },
      "mode": "lines",
      "textposition": "middle center",
      "type": "scatter",
      "x": [
        -0.830539,
        -0.303382
      ],
      "y": [
        -0.559033,
        -0.967419
      ]
    },
    {
      "hoverinfo": "none",
      "line": {
        "color": "#ff6f6f ",
        "shape": "linear",
        "width": 3.0
      },
      "mode": "lines",
      "textposition": "middle center",
      "type": "scatter",
      "x": [
        -0.303382,
        -0.830539
      ],
      "y": [
        -0.967419,
        -0.559033
      ]
    },
    {
      "hoverinfo": "none",
      "line": {
        "color": "#ff6f6f ",
        "shape": "linear",
        "width": 2.0
      },
      "mode": "lines",
      "textposition": "middle center",
      "type": "scatter",
      "x": [
        -0.830539,
        0.261182
      ],
      "y": [
        -0.559033,
        -0.703693
      ]
    },
    {
      "hoverinfo": "none",
      "line": {
        "color": "#ff6f6f ",
        "shape": "linear",
        "width": 2.0
      },
      "mode": "lines",
      "textposition": "middle center",
      "type": "scatter",
      "x": [
        0.261182,
        -0.830539
      ],
      "y": [
        -0.703693,
        -0.559033
      ]
    },
    {
      "hoverinfo": "none",
      "line": {
        "color": "#ff6f6f ",
        "shape": "linear",
        "width": 2.0
      },
      "mode": "lines",
      "textposition": "middle center",
      "type": "scatter",
      "x": [
        0.838057,
        -0.679827
      ],
      "y": [
        -0.28059,
        0.169582
      ]
    },
    {
      "hoverinfo": "none",
      "line": {
        "color": "#ff6f6f ",
        "shape": "linear",
        "width": 2.0
      },
      "mode": "lines",
      "textposition": "middle center",
      "type": "scatter",
      "x": [
        -0.679827,
        0.838057
      ],
      "y": [
        0.169582,
        -0.28059
      ]
    },
    {
      "hoverinfo": "none",
      "line": {
        "color": "#ff6f6f ",
        "shape": "linear",
        "width": 2.0
      },
      "mode": "lines",
      "textposition": "middle center",
      "type": "scatter",
      "x": [
        0.838057,
        -0.303382
      ],
      "y": [
        -0.28059,
        -0.967419
      ]
    },
    {
      "hoverinfo": "none",
      "line": {
        "color": "#ff6f6f ",
        "shape": "linear",
        "width": 2.0
      },
      "mode": "lines",
      "textposition": "middle center",
      "type": "scatter",
      "x": [
        -0.303382,
        0.838057
      ],
      "y": [
        -0.967419,
        -0.28059
      ]
    },
    {
      "hoverinfo": "none",
      "line": {
        "color": "#ff6f6f ",
        "shape": "linear",
        "width": 4.0
      },
      "mode": "lines",
      "textposition": "middle center",
      "type": "scatter",
      "x": [
        0.838057,
        0.810669
      ],
      "y": [
        -0.28059,
        -0.75292
      ]
    },
    {
      "hoverinfo": "none",
      "line": {
        "color": "#ff6f6f ",
        "shape": "linear",
        "width": 4.0
      },
      "mode": "lines",
      "textposition": "middle center",
      "type": "scatter",
      "x": [
        0.810669,
        0.838057
      ],
      "y": [
        -0.75292,
        -0.28059
      ]
    },
    {
      "hoverinfo": "none",
      "line": {
        "color": "#ff6f6f ",
        "shape": "linear",
        "width": 6.0
      },
      "mode": "lines",
      "textposition": "middle center",
      "type": "scatter",
      "x": [
        0.605424,
        0.261182
      ],
      "y": [
        -0.65289,
        -0.703693
      ]
    },
    {
      "hoverinfo": "none",
      "line": {
        "color": "#ff6f6f ",
        "shape": "linear",
        "width": 6.0
      },
      "mode": "lines",
      "textposition": "middle center",
      "type": "scatter",
      "x": [
        0.261182,
        0.605424
      ],
      "y": [
        -0.703693,
        -0.65289
      ]
    },
    {
      "hoverinfo": "none",
      "line": {
        "color": "#ff6f6f ",
        "shape": "linear",
        "width": 2.0
      },
      "mode": "lines",
      "textposition": "middle center",
      "type": "scatter",
      "x": [
        -0.679827,
        0.261182
      ],
      "y": [
        0.169582,
        -0.703693
      ]
    },
    {
      "hoverinfo": "none",
      "line": {
        "color": "#ff6f6f ",
        "shape": "linear",
        "width": 2.0
      },
      "mode": "lines",
      "textposition": "middle center",
      "type": "scatter",
      "x": [
        0.261182,
        -0.679827
      ],
      "y": [
        -0.703693,
        0.169582
      ]
    },
    {
      "hoverinfo": "none",
      "line": {
        "color": "#ff6f6f ",
        "shape": "linear",
        "width": 2.0
      },
      "mode": "lines",
      "textposition": "middle center",
      "type": "scatter",
      "x": [
        -0.679827,
        -0.298916
      ],
      "y": [
        0.169582,
        0.995379
      ]
    },
    {
      "hoverinfo": "none",
      "line": {
        "color": "#ff6f6f ",
        "shape": "linear",
        "width": 2.0
      },
      "mode": "lines",
      "textposition": "middle center",
      "type": "scatter",
      "x": [
        -0.298916,
        -0.679827
      ],
      "y": [
        0.995379,
        0.169582
      ]
    },
    {
      "hoverinfo": "none",
      "line": {
        "color": "#ff6f6f ",
        "shape": "linear",
        "width": 2.0
      },
      "mode": "lines",
      "textposition": "middle center",
      "type": "scatter",
      "x": [
        -0.303382,
        0.050432
      ],
      "y": [
        -0.967419,
        -0.91035
      ]
    },
    {
      "hoverinfo": "none",
      "line": {
        "color": "#ff6f6f ",
        "shape": "linear",
        "width": 2.0
      },
      "mode": "lines",
      "textposition": "middle center",
      "type": "scatter",
      "x": [
        0.050432,
        -0.303382
      ],
      "y": [
        -0.91035,
        -0.967419
      ]
    },
    {
      "hoverinfo": "none",
      "line": {
        "color": "#ff6f6f ",
        "shape": "linear",
        "width": 10.0
      },
      "mode": "lines",
      "textposition": "middle center",
      "type": "scatter",
      "x": [
        -0.303382,
        -0.542011
      ],
      "y": [
        -0.967419,
        -0.741446
      ]
    },
    {
      "hoverinfo": "none",
      "line": {
        "color": "#ff6f6f ",
        "shape": "linear",
        "width": 10.0
      },
      "mode": "lines",
      "textposition": "middle center",
      "type": "scatter",
      "x": [
        -0.542011,
        -0.303382
      ],
      "y": [
        -0.741446,
        -0.967419
      ]
    },
    {
      "hoverinfo": "none",
      "line": {
        "color": "#ff6f6f ",
        "shape": "linear",
        "width": 6.0
      },
      "mode": "lines",
      "textposition": "middle center",
      "type": "scatter",
      "x": [
        -0.303382,
        0.926226
      ],
      "y": [
        -0.967419,
        0.301567
      ]
    },
    {
      "hoverinfo": "none",
      "line": {
        "color": "#ff6f6f ",
        "shape": "linear",
        "width": 6.0
      },
      "mode": "lines",
      "textposition": "middle center",
      "type": "scatter",
      "x": [
        0.926226,
        -0.303382
      ],
      "y": [
        0.301567,
        -0.967419
      ]
    },
    {
      "hoverinfo": "none",
      "line": {
        "color": "#ff6f6f ",
        "shape": "linear",
        "width": 2.0
      },
      "mode": "lines",
      "textposition": "middle center",
      "type": "scatter",
      "x": [
        1.0,
        -0.10373
      ],
      "y": [
        -0.026633,
        0.787515
      ]
    },
    {
      "hoverinfo": "none",
      "line": {
        "color": "#ff6f6f ",
        "shape": "linear",
        "width": 2.0
      },
      "mode": "lines",
      "textposition": "middle center",
      "type": "scatter",
      "x": [
        -0.10373,
        1.0
      ],
      "y": [
        0.787515,
        -0.026633
      ]
    },
    {
      "hoverinfo": "none",
      "line": {
        "color": "#ff6f6f ",
        "shape": "spline",
        "width": 2.0
      },
      "mode": "lines",
      "textposition": "middle center",
      "type": "scatter",
      "x": [
        0.261182,
        0.16156790000000004,
        0.22797730000000002,
        0.261182
      ],
      "y": [
        -0.703693,
        -0.6704883,
        -0.6040789,
        -0.703693
      ]
    },
    {
      "hoverinfo": "none",
      "line": {
        "color": "#ff6f6f ",
        "shape": "spline",
        "width": 2.0
      },
      "mode": "lines",
      "textposition": "middle center",
      "type": "scatter",
      "x": [
        0.261182,
        0.16156790000000004,
        0.22797730000000002,
        0.261182
      ],
      "y": [
        -0.703693,
        -0.6704883,
        -0.6040789,
        -0.703693
      ]
    },
    {
      "hoverinfo": "none",
      "line": {
        "color": "#ff6f6f ",
        "shape": "linear",
        "width": 3.0
      },
      "mode": "lines",
      "textposition": "middle center",
      "type": "scatter",
      "x": [
        0.261182,
        0.810669
      ],
      "y": [
        -0.703693,
        -0.75292
      ]
    },
    {
      "hoverinfo": "none",
      "line": {
        "color": "#ff6f6f ",
        "shape": "linear",
        "width": 3.0
      },
      "mode": "lines",
      "textposition": "middle center",
      "type": "scatter",
      "x": [
        0.810669,
        0.261182
      ],
      "y": [
        -0.75292,
        -0.703693
      ]
    },
    {
      "hoverinfo": "none",
      "line": {
        "color": "#ff6f6f ",
        "shape": "spline",
        "width": 2.0
      },
      "mode": "lines",
      "textposition": "middle center",
      "type": "scatter",
      "x": [
        0.810669,
        0.7110548999999999,
        0.7774643,
        0.810669
      ],
      "y": [
        -0.75292,
        -0.7197153000000001,
        -0.6533059,
        -0.75292
      ]
    },
    {
      "hoverinfo": "none",
      "line": {
        "color": "#ff6f6f ",
        "shape": "spline",
        "width": 2.0
      },
      "mode": "lines",
      "textposition": "middle center",
      "type": "scatter",
      "x": [
        0.810669,
        0.7110548999999999,
        0.7774643,
        0.810669
      ],
      "y": [
        -0.75292,
        -0.7197153000000001,
        -0.6533059,
        -0.75292
      ]
    },
    {
      "hoverinfo": "none",
      "line": {
        "color": "#ff6f6f ",
        "shape": "linear",
        "width": 3.0
      },
      "mode": "lines",
      "textposition": "middle center",
      "type": "scatter",
      "x": [
        0.536248,
        -0.10373
      ],
      "y": [
        0.747885,
        0.787515
      ]
    },
    {
      "hoverinfo": "none",
      "line": {
        "color": "#ff6f6f ",
        "shape": "linear",
        "width": 3.0
      },
      "mode": "lines",
      "textposition": "middle center",
      "type": "scatter",
      "x": [
        -0.10373,
        0.536248
      ],
      "y": [
        0.787515,
        0.747885
      ]
    },
    {
      "hoverinfo": "text",
      "hovertext": [
        "<b>I1L</b><br>Pharyngeal interneuron<br>Conns in: <b>I2L</b>: 2, <b>M3L</b>: 1, <b>MCR</b>: 1<br>Conns out: <b>I2L</b>: 2, <b>M3L</b>: 1, <b>MCR</b>: 1",
        "<b>I1R</b><br>Pharyngeal interneuron<br>Conns in: <b>MCR</b>: 4, <b>NSMR</b>: 2, <b>I3</b>: 1<br>Conns out: <b>MCR</b>: 4, <b>NSMR</b>: 2, <b>I3</b>: 1",
        "<b>I2L</b><br>Pharyngeal interneuron<br>Conns in: <b>I1L</b>: 2, <b>M2L</b>: 1<br>Conns out: <b>I1L</b>: 2, <b>M2L</b>: 1",
        "<b>I2R</b><br>Pharyngeal interneuron<br>Conns in: <b>NSMR</b>: 2, <b>M1</b>: 1, <b>M2R</b>: 1<br>Conns out: <b>NSMR</b>: 2, <b>M1</b>: 1, <b>M2R</b>: 1",
        "<b>I3</b><br>Pharyngeal interneuron<br>Conns in: <b>I1R</b>: 1, <b>M1</b>: 1, <b>MI</b>: 1<br>Conns out: <b>I1R</b>: 1, <b>M1</b>: 1, <b>MI</b>: 1",
        "<b>I4</b><br>Pharyngeal interneuron<br>Conns in: <b>M2R</b>: 2, <b>M4</b>: 1<br>Conns out: <b>M2R</b>: 2, <b>M4</b>: 1",
        "<b>I5</b><br>Pharyngeal interneuron<br>Conns in: <b>M5</b>: 3, <b>M2L</b>: 1, <b>M2R</b>: 1<br>Conns out: <b>M5</b>: 3, <b>M2L</b>: 1, <b>M2R</b>: 1",
        "<b>I6</b><br>Pharyngeal interneuron<br>Conns in: <b>M4</b>: 5<br>Conns out: <b>M4</b>: 5",
        "<b>M1</b><br>Pharyngeal motor neuron<br>Conns in: <b>I2R</b>: 1, <b>I3</b>: 1<br>Conns out: <b>I2R</b>: 1, <b>I3</b>: 1",
        "<b>M2L</b><br>Pharyngeal motor neuron<br>Conns in: <b>I2L</b>: 1, <b>I5</b>: 1, <b>M4</b>: 1, <b>MCL</b>: 1<br>Conns out: <b>I2L</b>: 1, <b>I5</b>: 1, <b>M4</b>: 1, <b>MCL</b>: 1",
        "<b>M2R</b><br>Pharyngeal motor neuron<br>Conns in: <b>MCR</b>: 9, <b>MI</b>: 5, <b>I4</b>: 2, <b>I2R</b>: 1, <b>I5</b>: 1, <b>M3R</b>: 1<br>Conns out: <b>MCR</b>: 9, <b>MI</b>: 5, <b>I4</b>: 2, <b>I2R</b>: 1, <b>I5</b>: 1, <b>M3R</b>: 1",
        "<b>M3L</b><br>Pharyngeal motor neuron<br>Conns in: <b>I1L</b>: 1, <b>NSMR</b>: 1<br>Conns out: <b>I1L</b>: 1, <b>NSMR</b>: 1",
        "<b>M3R</b><br>Pharyngeal motor neuron<br>Conns in: <b>M2R</b>: 1<br>Conns out: <b>M2R</b>: 1",
        "<b>M4</b><br>Pharyngeal motor neuron<br>Conns in: <b>I6</b>: 5, <b>M5</b>: 2, <b>I4</b>: 1, <b>M2L</b>: 1, <b>M4</b>: 1<br>Conns out: <b>I6</b>: 5, <b>M5</b>: 2, <b>I4</b>: 1, <b>M2L</b>: 1, <b>M4</b>: 1",
        "<b>M5</b><br>Pharyngeal motor neuron<br>Conns in: <b>I5</b>: 3, <b>M4</b>: 2, <b>M5</b>: 1<br>Conns out: <b>I5</b>: 3, <b>M4</b>: 2, <b>M5</b>: 1",
        "<b>MCL</b><br>Pharyngeal polymodal neuron<br>Conns in: <b>M2L</b>: 1<br>Conns out: <b>M2L</b>: 1",
        "<b>MCR</b><br>Pharyngeal polymodal neuron<br>Conns in: <b>M2R</b>: 9, <b>I1R</b>: 4, <b>I1L</b>: 1<br>Conns out: <b>M2R</b>: 9, <b>I1R</b>: 4, <b>I1L</b>: 1",
        "<b>MI</b><br>Pharyngeal polymodal neuron<br>Conns in: <b>M2R</b>: 5, <b>I3</b>: 1<br>Conns out: <b>M2R</b>: 5, <b>I3</b>: 1",
        "<b>NSML</b><br>Pharyngeal polymodal neuron<br>Conns in: <b>NSMR</b>: 2<br>Conns out: <b>NSMR</b>: 2",
        "<b>NSMR</b><br>Pharyngeal polymodal neuron<br>Conns in: <b>I1R</b>: 2, <b>I2R</b>: 2, <b>NSML</b>: 2, <b>M3L</b>: 1<br>Conns out: <b>I1R</b>: 2, <b>I2R</b>: 2, <b>NSML</b>: 2, <b>M3L</b>: 1"
      ],
      "marker": {
        "color": [
          "#ff3300",
          "#ff3300",
          "#ff3300",
          "#ff3300",
          "#ff3300",
          "#ff3300",
          "#ff3300",
          "#ff3300",
          "#9966cc",
          "#9966cc",
          "#9966cc",
          "#9966cc",
          "#9966cc",
          "#9966cc",
          "#9966cc",
          "#cc0033",
          "#cc0033",
          "#cc0033",
          "#cc0033",
          "#cc0033"
        ],
        "colorbar": {
          "thickness": 15,
          "title": {
            "text": "Node Connections"
          },
          "xanchor": "left"
        },
        "colorscale": [
          [
            0.0,
            "rgb(255,255,217)"
          ],
          [
            0.125,
            "rgb(237,248,177)"
          ],
          [
            0.25,
            "rgb(199,233,180)"
          ],
          [
            0.375,
            "rgb(127,205,187)"
          ],
          [
            0.5,
            "rgb(65,182,196)"
          ],
          [
            0.625,
            "rgb(29,145,192)"
          ],
          [
            0.75,
            "rgb(34,94,168)"
          ],
          [
            0.875,
            "rgb(37,52,148)"
          ],
          [
            1.0,
            "rgb(8,29,88)"
          ]
        ],
        "line": {
          "width": 1
        },
        "reversescale": true,
        "showscale": false,
        "size": [
          15.0,
          15.0,
          15.0,
          15.0,
          15.0,
          15.0,
          15.0,
          15.0,
          15.0,
          15.0,
          15.0,
          15.0,
          15.0,
          15.0,
          15.0,
          15.0,
          15.0,
          15.0,
          15.0,
          15.0
        ],
        "symbol": [
          "circle",
          "circle",
          "circle",
          "circle",
          "circle",
          "circle",
          "circle",
          "circle",
          "circle",
          "circle",
          "circle",
          "circle",
          "circle",
          "circle",
          "circle",
          "circle",
          "circle",
          "circle",
          "circle",
          "circle"
        ]
      },
      "mode": "markers",
      "opacity": 1,
      "text": [
        "<span style=\"color:#000000;font-size:1.0em\"><b>I1L</b></span>",
        "<span style=\"color:#000000;font-size:1.0em\"><b>I1R</b></span>",
        "<span style=\"color:#000000;font-size:1.0em\"><b>I2L</b></span>",
        "<span style=\"color:#000000;font-size:1.0em\"><b>I2R</b></span>",
        "<span style=\"color:#000000;font-size:1.0em\"><b>I3</b></span>",
        "<span style=\"color:#000000;font-size:1.0em\"><b>I4</b></span>",
        "<span style=\"color:#000000;font-size:1.0em\"><b>I5</b></span>",
        "<span style=\"color:#000000;font-size:1.0em\"><b>I6</b></span>",
        "<span style=\"color:#000000;font-size:1.0em\"><b>M1</b></span>",
        "<span style=\"color:#000000;font-size:1.0em\"><b>M2L</b></span>",
        "<span style=\"color:#000000;font-size:1.0em\"><b>M2R</b></span>",
        "<span style=\"color:#000000;font-size:1.0em\"><b>M3L</b></span>",
        "<span style=\"color:#000000;font-size:1.0em\"><b>M3R</b></span>",
        "<span style=\"color:#000000;font-size:1.0em\"><b>M4</b></span>",
        "<span style=\"color:#000000;font-size:1.0em\"><b>M5</b></span>",
        "<span style=\"color:#ffffff;font-size:1.0em\"><b>MCL</b></span>",
        "<span style=\"color:#ffffff;font-size:1.0em\"><b>MCR</b></span>",
        "<span style=\"color:#ffffff;font-size:1.0em\"><b>MI</b></span>",
        "<span style=\"color:#ffffff;font-size:1.0em\"><b>NSML</b></span>",
        "<span style=\"color:#ffffff;font-size:1.0em\"><b>NSMR</b></span>"
      ],
      "textposition": "middle center",
      "type": "scatter",
      "x": [
        -0.852778,
        -0.920991,
        -0.637271,
        -0.992282,
        0.895121,
        -0.830539,
        0.838057,
        0.605424,
        0.238369,
        -0.679827,
        -0.303382,
        1.0,
        0.050432,
        0.261182,
        0.810669,
        -0.298916,
        -0.542011,
        0.926226,
        0.536248,
        -0.10373
      ],
      "y": [
        0.440177,
        -0.258648,
        0.736826,
        0.076038,
        0.609387,
        -0.559033,
        -0.28059,
        -0.65289,
        0.989267,
        0.169582,
        -0.967419,
        -0.026633,
        -0.91035,
        -0.703693,
        -0.75292,
        0.995379,
        -0.741446,
        0.301567,
        0.747885,
        0.787515
      ]
    }
  ],
  "layout": {
    "height": 800,
    "hovermode": "closest",
    "margin": {
      "b": 20,
      "l": 5,
      "r": 5,
      "t": 40
    },
    "showlegend": false,
    "template": {
      "data": {
        "bar": [
          {
            "error_x": {
              "color": "#2a3f5f"
            },
            "error_y": {
              "color": "#2a3f5f"
            },
            "marker": {
              "line": {
                "color": "white",
                "width": 0.5
              },
              "pattern": {
                "fillmode": "overlay",
                "size": 10,
                "solidity": 0.2
              }
            },
            "type": "bar"
          }
        ],
        "barpolar": [
          {
            "marker": {
              "line": {
                "color": "white",
                "width": 0.5
              },
              "pattern": {
                "fillmode": "overlay",
                "size": 10,
                "solidity": 0.2
              }
            },
            "type": "barpolar"
          }
        ],
        "carpet": [
          {
            "aaxis": {
              "endlinecolor": "#2a3f5f",
              "gridcolor": "#C8D4E3",
              "linecolor": "#C8D4E3",
              "minorgridcolor": "#C8D4E3",
              "startlinecolor": "#2a3f5f"
            },
            "baxis": {
              "endlinecolor": "#2a3f5f",
              "gridcolor": "#C8D4E3",
              "linecolor": "#C8D4E3",
              "minorgridcolor": "#C8D4E3",
              "startlinecolor": "#2a3f5f"
            },
            "type": "carpet"
          }
        ],
        "choropleth": [
          {
            "colorbar": {
              "outlinewidth": 0,
              "ticks": ""
            },
            "type": "choropleth"
          }
        ],
        "contour": [
          {
            "colorbar": {
              "outlinewidth": 0,
              "ticks": ""
            },
            "colorscale": [
              [
                0.0,
                "#0d0887"
              ],
              [
                0.1111111111111111,
                "#46039f"
              ],
              [
                0.2222222222222222,
                "#7201a8"
              ],
              [
                0.3333333333333333,
                "#9c179e"
              ],
              [
                0.4444444444444444,
                "#bd3786"
              ],
              [
                0.5555555555555556,
                "#d8576b"
              ],
              [
                0.6666666666666666,
                "#ed7953"
              ],
              [
                0.7777777777777778,
                "#fb9f3a"
              ],
              [
                0.8888888888888888,
                "#fdca26"
              ],
              [
                1.0,
                "#f0f921"
              ]
            ],
            "type": "contour"
          }
        ],
        "contourcarpet": [
          {
            "colorbar": {
              "outlinewidth": 0,
              "ticks": ""
            },
            "type": "contourcarpet"
          }
        ],
        "heatmap": [
          {
            "colorbar": {
              "outlinewidth": 0,
              "ticks": ""
            },
            "colorscale": [
              [
                0.0,
                "#0d0887"
              ],
              [
                0.1111111111111111,
                "#46039f"
              ],
              [
                0.2222222222222222,
                "#7201a8"
              ],
              [
                0.3333333333333333,
                "#9c179e"
              ],
              [
                0.4444444444444444,
                "#bd3786"
              ],
              [
                0.5555555555555556,
                "#d8576b"
              ],
              [
                0.6666666666666666,
                "#ed7953"
              ],
              [
                0.7777777777777778,
                "#fb9f3a"
              ],
              [
                0.8888888888888888,
                "#fdca26"
              ],
              [
                1.0,
                "#f0f921"
              ]
            ],
            "type": "heatmap"
          }
        ],
        "heatmapgl": [
          {
            "colorbar": {
              "outlinewidth": 0,
              "ticks": ""
            },
            "colorscale": [
              [
                0.0,
                "#0d0887"
              ],
              [
                0.1111111111111111,
                "#46039f"
              ],
              [
                0.2222222222222222,
                "#7201a8"
              ],
              [
                0.3333333333333333,
                "#9c179e"
              ],
              [
                0.4444444444444444,
                "#bd3786"
              ],
              [
                0.5555555555555556,
                "#d8576b"
              ],
              [
                0.6666666666666666,
                "#ed7953"
              ],
              [
                0.7777777777777778,
                "#fb9f3a"
              ],
              [
                0.8888888888888888,
                "#fdca26"
              ],
              [
                1.0,
                "#f0f921"
              ]
            ],
            "type": "heatmapgl"
          }
        ],
        "histogram": [
          {
            "marker": {
              "pattern": {
                "fillmode": "overlay",
                "size": 10,
                "solidity": 0.2
              }
            },
            "type": "histogram"
          }
        ],
        "histogram2d": [
          {
            "colorbar": {
              "outlinewidth": 0,
              "ticks": ""
            },
            "colorscale": [
              [
                0.0,
                "#0d0887"
              ],
              [
                0.1111111111111111,
                "#46039f"
              ],
              [
                0.2222222222222222,
                "#7201a8"
              ],
              [
                0.3333333333333333,
                "#9c179e"
              ],
              [
                0.4444444444444444,
                "#bd3786"
              ],
              [
                0.5555555555555556,
                "#d8576b"
              ],
              [
                0.6666666666666666,
                "#ed7953"
              ],
              [
                0.7777777777777778,
                "#fb9f3a"
              ],
              [
                0.8888888888888888,
                "#fdca26"
              ],
              [
                1.0,
                "#f0f921"
              ]
            ],
            "type": "histogram2d"
          }
        ],
        "histogram2dcontour": [
          {
            "colorbar": {
              "outlinewidth": 0,
              "ticks": ""
            },
            "colorscale": [
              [
                0.0,
                "#0d0887"
              ],
              [
                0.1111111111111111,
                "#46039f"
              ],
              [
                0.2222222222222222,
                "#7201a8"
              ],
              [
                0.3333333333333333,
                "#9c179e"
              ],
              [
                0.4444444444444444,
                "#bd3786"
              ],
              [
                0.5555555555555556,
                "#d8576b"
              ],
              [
                0.6666666666666666,
                "#ed7953"
              ],
              [
                0.7777777777777778,
                "#fb9f3a"
              ],
              [
                0.8888888888888888,
                "#fdca26"
              ],
              [
                1.0,
                "#f0f921"
              ]
            ],
            "type": "histogram2dcontour"
          }
        ],
        "mesh3d": [
          {
            "colorbar": {
              "outlinewidth": 0,
              "ticks": ""
            },
            "type": "mesh3d"
          }
        ],
        "parcoords": [
          {
            "line": {
              "colorbar": {
                "outlinewidth": 0,
                "ticks": ""
              }
            },
            "type": "parcoords"
          }
        ],
        "pie": [
          {
            "automargin": true,
            "type": "pie"
          }
        ],
        "scatter": [
          {
            "fillpattern": {
              "fillmode": "overlay",
              "size": 10,
              "solidity": 0.2
            },
            "type": "scatter"
          }
        ],
        "scatter3d": [
          {
            "line": {
              "colorbar": {
                "outlinewidth": 0,
                "ticks": ""
              }
            },
            "marker": {
              "colorbar": {
                "outlinewidth": 0,
                "ticks": ""
              }
            },
            "type": "scatter3d"
          }
        ],
        "scattercarpet": [
          {
            "marker": {
              "colorbar": {
                "outlinewidth": 0,
                "ticks": ""
              }
            },
            "type": "scattercarpet"
          }
        ],
        "scattergeo": [
          {
            "marker": {
              "colorbar": {
                "outlinewidth": 0,
                "ticks": ""
              }
            },
            "type": "scattergeo"
          }
        ],
        "scattergl": [
          {
            "marker": {
              "colorbar": {
                "outlinewidth": 0,
                "ticks": ""
              }
            },
            "type": "scattergl"
          }
        ],
        "scattermapbox": [
          {
            "marker": {
              "colorbar": {
                "outlinewidth": 0,
                "ticks": ""
              }
            },
            "type": "scattermapbox"
          }
        ],
        "scatterpolar": [
          {
            "marker": {
              "colorbar": {
                "outlinewidth": 0,
                "ticks": ""
              }
            },
            "type": "scatterpolar"
          }
        ],
        "scatterpolargl": [
          {
            "marker": {
              "colorbar": {
                "outlinewidth": 0,
                "ticks": ""
              }
            },
            "type": "scatterpolargl"
          }
        ],
        "scatterternary": [
          {
            "marker": {
              "colorbar": {
                "outlinewidth": 0,
                "ticks": ""
              }
            },
            "type": "scatterternary"
          }
        ],
        "surface": [
          {
            "colorbar": {
              "outlinewidth": 0,
              "ticks": ""
            },
            "colorscale": [
              [
                0.0,
                "#0d0887"
              ],
              [
                0.1111111111111111,
                "#46039f"
              ],
              [
                0.2222222222222222,
                "#7201a8"
              ],
              [
                0.3333333333333333,
                "#9c179e"
              ],
              [
                0.4444444444444444,
                "#bd3786"
              ],
              [
                0.5555555555555556,
                "#d8576b"
              ],
              [
                0.6666666666666666,
                "#ed7953"
              ],
              [
                0.7777777777777778,
                "#fb9f3a"
              ],
              [
                0.8888888888888888,
                "#fdca26"
              ],
              [
                1.0,
                "#f0f921"
              ]
            ],
            "type": "surface"
          }
        ],
        "table": [
          {
            "cells": {
              "fill": {
                "color": "#EBF0F8"
              },
              "line": {
                "color": "white"
              }
            },
            "header": {
              "fill": {
                "color": "#C8D4E3"
              },
              "line": {
                "color": "white"
              }
            },
            "type": "table"
          }
        ]
      },
      "layout": {
        "annotationdefaults": {
          "arrowcolor": "#2a3f5f",
          "arrowhead": 0,
          "arrowwidth": 1
        },
        "autotypenumbers": "strict",
        "coloraxis": {
          "colorbar": {
            "outlinewidth": 0,
            "ticks": ""
          }
        },
        "colorscale": {
          "diverging": [
            [
              0,
              "#8e0152"
            ],
            [
              0.1,
              "#c51b7d"
            ],
            [
              0.2,
              "#de77ae"
            ],
            [
              0.3,
              "#f1b6da"
            ],
            [
              0.4,
              "#fde0ef"
            ],
            [
              0.5,
              "#f7f7f7"
            ],
            [
              0.6,
              "#e6f5d0"
            ],
            [
              0.7,
              "#b8e186"
            ],
            [
              0.8,
              "#7fbc41"
            ],
            [
              0.9,
              "#4d9221"
            ],
            [
              1,
              "#276419"
            ]
          ],
          "sequential": [
            [
              0.0,
              "#0d0887"
            ],
            [
              0.1111111111111111,
              "#46039f"
            ],
            [
              0.2222222222222222,
              "#7201a8"
            ],
            [
              0.3333333333333333,
              "#9c179e"
            ],
            [
              0.4444444444444444,
              "#bd3786"
            ],
            [
              0.5555555555555556,
              "#d8576b"
            ],
            [
              0.6666666666666666,
              "#ed7953"
            ],
            [
              0.7777777777777778,
              "#fb9f3a"
            ],
            [
              0.8888888888888888,
              "#fdca26"
            ],
            [
              1.0,
              "#f0f921"
            ]
          ],
          "sequentialminus": [
            [
              0.0,
              "#0d0887"
            ],
            [
              0.1111111111111111,
              "#46039f"
            ],
            [
              0.2222222222222222,
              "#7201a8"
            ],
            [
              0.3333333333333333,
              "#9c179e"
            ],
            [
              0.4444444444444444,
              "#bd3786"
            ],
            [
              0.5555555555555556,
              "#d8576b"
            ],
            [
              0.6666666666666666,
              "#ed7953"
            ],
            [
              0.7777777777777778,
              "#fb9f3a"
            ],
            [
              0.8888888888888888,
              "#fdca26"
            ],
            [
              1.0,
              "#f0f921"
            ]
          ]
        },
        "colorway": [
          "#636efa",
          "#EF553B",
          "#00cc96",
          "#ab63fa",
          "#FFA15A",
          "#19d3f3",
          "#FF6692",
          "#B6E880",
          "#FF97FF",
          "#FECB52"
        ],
        "font": {
          "color": "#2a3f5f"
        },
        "geo": {
          "bgcolor": "white",
          "lakecolor": "white",
          "landcolor": "white",
          "showlakes": true,
          "showland": true,
          "subunitcolor": "#C8D4E3"
        },
        "hoverlabel": {
          "align": "left"
        },
        "hovermode": "closest",
        "mapbox": {
          "style": "light"
        },
        "paper_bgcolor": "white",
        "plot_bgcolor": "white",
        "polar": {
          "angularaxis": {
            "gridcolor": "#EBF0F8",
            "linecolor": "#EBF0F8",
            "ticks": ""
          },
          "bgcolor": "white",
          "radialaxis": {
            "gridcolor": "#EBF0F8",
            "linecolor": "#EBF0F8",
            "ticks": ""
          }
        },
        "scene": {
          "xaxis": {
            "backgroundcolor": "white",
            "gridcolor": "#DFE8F3",
            "gridwidth": 2,
            "linecolor": "#EBF0F8",
            "showbackground": true,
            "ticks": "",
            "zerolinecolor": "#EBF0F8"
          },
          "yaxis": {
            "backgroundcolor": "white",
            "gridcolor": "#DFE8F3",
            "gridwidth": 2,
            "linecolor": "#EBF0F8",
            "showbackground": true,
            "ticks": "",
            "zerolinecolor": "#EBF0F8"
          },
          "zaxis": {
            "backgroundcolor": "white",
            "gridcolor": "#DFE8F3",
            "gridwidth": 2,
            "linecolor": "#EBF0F8",
            "showbackground": true,
            "ticks": "",
            "zerolinecolor": "#EBF0F8"
          }
        },
        "shapedefaults": {
          "line": {
            "color": "#2a3f5f"
          }
        },
        "ternary": {
          "aaxis": {
            "gridcolor": "#DFE8F3",
            "linecolor": "#A2B1C6",
            "ticks": ""
          },
          "baxis": {
            "gridcolor": "#DFE8F3",
            "linecolor": "#A2B1C6",
            "ticks": ""
          },
          "bgcolor": "white",
          "caxis": {
            "gridcolor": "#DFE8F3",
            "linecolor": "#A2B1C6",
            "ticks": ""
          }
        },
        "title": {
          "x": 0.05
        },
        "xaxis": {
          "automargin": true,
          "gridcolor": "#EBF0F8",
          "linecolor": "#EBF0F8",
          "ticks": "",
          "title": {
            "standoff": 15
          },
          "zerolinecolor": "#EBF0F8",
          "zerolinewidth": 2
        },
        "yaxis": {
          "automargin": true,
          "gridcolor": "#EBF0F8",
          "linecolor": "#EBF0F8",
          "ticks": "",
          "title": {
            "standoff": 15
          },
          "zerolinecolor": "#EBF0F8",
          "zerolinewidth": 2
        }
      }
    },
    "width": 800,
    "xaxis": {
      "showgrid": false,
      "visible": false,
      "zeroline": false
    },
    "yaxis": {
      "scaleanchor": "x",
      "scaleratio": 1,
      "showgrid": false,
      "visible": false,
      "zeroline": false
    }
  }
}