{
  "data": [
    {
      "hoverinfo": "none",
      "line": {
        "color": "#ff6f6f ",
        "shape": "linear",
        "width": 5.5
      },
      "mode": "lines",
      "textposition": "middle center",
      "type": "scatter",
      "x": [
        -0.373632,
        0.404669
      ],
      "y": [
        0.912747,
        -0.929351
      ]
    },
    {
      "hoverinfo": "none",
      "line": {
        "color": "#ff6f6f ",
        "shape": "linear",
        "width": 5.5
      },
      "mode": "lines",
      "textposition": "middle center",
      "type": "scatter",
      "x": [
        0.404669,
        -0.373632
      ],
      "y": [
        -0.929351,
        0.912747
      ]
    },
    {
      "hoverinfo": "none",
      "line": {
        "color": "#ff6f6f ",
        "shape": "linear",
        "width": 5.5
      },
      "mode": "lines",
      "textposition": "middle center",
      "type": "scatter",
      "x": [
        -0.373632,
        0.83102
      ],
      "y": [
        0.912747,
        -0.540672
      ]
    },
    {
      "hoverinfo": "none",
      "line": {
        "color": "#ff6f6f ",
        "shape": "linear",
        "width": 5.5
      },
      "mode": "lines",
      "textposition": "middle center",
      "type": "scatter",
      "x": [
        0.83102,
        -0.373632
      ],
      "y": [
        -0.540672,
        0.912747
      ]
    },
    {
      "hoverinfo": "none",
      "line": {
        "color": "#ff6f6f ",
        "shape": "linear",
        "width": 5.5
      },
      "mode": "lines",
      "textposition": "middle center",
      "type": "scatter",
      "x": [
        0.785876,
        0.873495
      ],
      "y": [
        -0.230606,
        -0.622643
      ]
    },
    {
      "hoverinfo": "none",
      "line": {
        "color": "#ff6f6f ",
        "shape": "linear",
        "width": 5.5
      },
      "mode": "lines",
      "textposition": "middle center",
      "type": "scatter",
      "x": [
        0.873495,
        0.785876
      ],
      "y": [
        -0.622643,
        -0.230606
      ]
    },
    {
      "hoverinfo": "none",
      "line": {
        "color": "#ff6f6f ",
        "shape": "linear",
        "width": 5.5
      },
      "mode": "lines",
      "textposition": "middle center",
      "type": "scatter",
      "x": [
        0.785876,
        0.857336
      ],
      "y": [
        -0.230606,
        0.23011
      ]
    },
    {
      "hoverinfo": "none",
      "line": {
        "color": "#ff6f6f ",
        "shape": "linear",
        "width": 5.5
      },
      "mode": "lines",
      "textposition": "middle center",
      "type": "scatter",
      "x": [
        0.857336,
        0.785876
      ],
      "y": [
        0.23011,
        -0.230606
      ]
    },
    {
      "hoverinfo": "none",
      "line": {
        "color": "#ff6f6f ",
        "shape": "linear",
        "width": 5.5
      },
      "mode": "lines",
      "textposition": "middle center",
      "type": "scatter",
      "x": [
        0.785876,
        -0.607724
      ],
      "y": [
        -0.230606,
        -0.568064
      ]
    },
    {
      "hoverinfo": "none",
      "line": {
        "color": "#ff6f6f ",
        "shape": "linear",
        "width": 5.5
      },
      "mode": "lines",
      "textposition": "middle center",
      "type": "scatter",
      "x": [
        -0.607724,
        0.785876
      ],
      "y": [
        -0.568064,
        -0.230606
      ]
    },
    {
      "hoverinfo": "none",
      "line": {
        "color": "#ff6f6f ",
        "shape": "linear",
        "width": 5.5
      },
      "mode": "lines",
      "textposition": "middle center",
      "type": "scatter",
      "x": [
        0.785876,
        0.824025
      ],
      "y": [
        -0.230606,
        -0.424502
      ]
    },
    {
      "hoverinfo": "none",
      "line": {
        "color": "#ff6f6f ",
        "shape": "linear",
        "width": 5.5
      },
      "mode": "lines",
      "textposition": "middle center",
      "type": "scatter",
      "x": [
        0.824025,
        0.785876
      ],
      "y": [
        -0.424502,
        -0.230606
      ]
    },
    {
      "hoverinfo": "none",
      "line": {
        "color": "#ff6f6f ",
        "shape": "linear",
        "width": 5.5
      },
      "mode": "lines",
      "textposition": "middle center",
      "type": "scatter",
      "x": [
        -0.633697,
        0.857336
      ],
      "y": [
        -0.419642,
        0.23011
      ]
    },
    {
      "hoverinfo": "none",
      "line": {
        "color": "#ff6f6f ",
        "shape": "linear",
        "width": 5.5
      },
      "mode": "lines",
      "textposition": "middle center",
      "type": "scatter",
      "x": [
        0.857336,
        -0.633697
      ],
      "y": [
        0.23011,
        -0.419642
      ]
    },
    {
      "hoverinfo": "none",
      "line": {
        "color": "#ff6f6f ",
        "shape": "linear",
        "width": 5.5
      },
      "mode": "lines",
      "textposition": "middle center",
      "type": "scatter",
      "x": [
        -0.633697,
        0.84436
      ],
      "y": [
        -0.419642,
        0.534896
      ]
    },
    {
      "hoverinfo": "none",
      "line": {
        "color": "#ff6f6f ",
        "shape": "linear",
        "width": 5.5
      },
      "mode": "lines",
      "textposition": "middle center",
      "type": "scatter",
      "x": [
        0.84436,
        -0.633697
      ],
      "y": [
        0.534896,
        -0.419642
      ]
    },
    {
      "hoverinfo": "none",
      "line": {
        "color": "#ff6f6f ",
        "shape": "linear",
        "width": 5.5
      },
      "mode": "lines",
      "textposition": "middle center",
      "type": "scatter",
      "x": [
        -0.633697,
        0.935388
      ],
      "y": [
        -0.419642,
        0.353421
      ]
    },
    {
      "hoverinfo": "none",
      "line": {
        "color": "#ff6f6f ",
        "shape": "linear",
        "width": 5.5
      },
      "mode": "lines",
      "textposition": "middle center",
      "type": "scatter",
      "x": [
        0.935388,
        -0.633697
      ],
      "y": [
        0.353421,
        -0.419642
      ]
    },
    {
      "hoverinfo": "none",
      "line": {
        "color": "#ff6f6f ",
        "shape": "linear",
        "width": 5.5
      },
      "mode": "lines",
      "textposition": "middle center",
      "type": "scatter",
      "x": [
        -0.633697,
        -1.0
      ],
      "y": [
        -0.419642,
        -0.023996
      ]
    },
    {
      "hoverinfo": "none",
      "line": {
        "color": "#ff6f6f ",
        "shape": "linear",
        "width": 5.5
      },
      "mode": "lines",
      "textposition": "middle center",
      "type": "scatter",
      "x": [
        -1.0,
        -0.633697
      ],
      "y": [
        -0.023996,
        -0.419642
      ]
    },
    {
      "hoverinfo": "none",
      "line": {
        "color": "#ff6f6f ",
        "shape": "linear",
        "width": 5.5
      },
      "mode": "lines",
      "textposition": "middle center",
      "type": "scatter",
      "x": [
        -0.633697,
        0.83102
      ],
      "y": [
        -0.419642,
        -0.540672
      ]
    },
    {
      "hoverinfo": "none",
      "line": {
        "color": "#ff6f6f ",
        "shape": "linear",
        "width": 5.5
      },
      "mode": "lines",
      "textposition": "middle center",
      "type": "scatter",
      "x": [
        0.83102,
        -0.633697
      ],
      "y": [
        -0.540672,
        -0.419642
      ]
    },
    {
      "hoverinfo": "none",
      "line": {
        "color": "#ff6f6f ",
        "shape": "linear",
        "width": 5.5
      },
      "mode": "lines",
      "textposition": "middle center",
      "type": "scatter",
      "x": [
        -0.633697,
        0.975852
      ],
      "y": [
        -0.419642,
        -0.041317
      ]
    },
    {
      "hoverinfo": "none",
      "line": {
        "color": "#ff6f6f ",
        "shape": "linear",
        "width": 5.5
      },
      "mode": "lines",
      "textposition": "middle center",
      "type": "scatter",
      "x": [
        0.975852,
        -0.633697
      ],
      "y": [
        -0.041317,
        -0.419642
      ]
    },
    {
      "hoverinfo": "none",
      "line": {
        "color": "#ff6f6f ",
        "shape": "linear",
        "width": 5.5
      },
      "mode": "lines",
      "textposition": "middle center",
      "type": "scatter",
      "x": [
        0.873495,
        -0.567745
      ],
      "y": [
        -0.622643,
        0.880354
      ]
    },
    {
      "hoverinfo": "none",
      "line": {
        "color": "#ff6f6f ",
        "shape": "linear",
        "width": 5.5
      },
      "mode": "lines",
      "textposition": "middle center",
      "type": "scatter",
      "x": [
        -0.567745,
        0.873495
      ],
      "y": [
        0.880354,
        -0.622643
      ]
    },
    {
      "hoverinfo": "none",
      "line": {
        "color": "#ff6f6f ",
        "shape": "linear",
        "width": 5.5
      },
      "mode": "lines",
      "textposition": "middle center",
      "type": "scatter",
      "x": [
        0.873495,
        0.975852
      ],
      "y": [
        -0.622643,
        -0.041317
      ]
    },
    {
      "hoverinfo": "none",
      "line": {
        "color": "#ff6f6f ",
        "shape": "linear",
        "width": 5.5
      },
      "mode": "lines",
      "textposition": "middle center",
      "type": "scatter",
      "x": [
        0.975852,
        0.873495
      ],
      "y": [
        -0.041317,
        -0.622643
      ]
    },
    {
      "hoverinfo": "none",
      "line": {
        "color": "#ff6f6f ",
        "shape": "linear",
        "width": 5.5
      },
      "mode": "lines",
      "textposition": "middle center",
      "type": "scatter",
      "x": [
        0.857336,
        0.84436
      ],
      "y": [
        0.23011,
        0.534896
      ]
    },
    {
      "hoverinfo": "none",
      "line": {
        "color": "#ff6f6f ",
        "shape": "linear",
        "width": 5.5
      },
      "mode": "lines",
      "textposition": "middle center",
      "type": "scatter",
      "x": [
        0.84436,
        0.857336
      ],
      "y": [
        0.534896,
        0.23011
      ]
    },
    {
      "hoverinfo": "none",
      "line": {
        "color": "#ff6f6f ",
        "shape": "linear",
        "width": 5.5
      },
      "mode": "lines",
      "textposition": "middle center",
      "type": "scatter",
      "x": [
        -0.567745,
        0.189696
      ],
      "y": [
        0.880354,
        0.974109
      ]
    },
    {
      "hoverinfo": "none",
      "line": {
        "color": "#ff6f6f ",
        "shape": "linear",
        "width": 5.5
      },
      "mode": "lines",
      "textposition": "middle center",
      "type": "scatter",
      "x": [
        0.189696,
        -0.567745
      ],
      "y": [
        0.974109,
        0.880354
      ]
    },
    {
      "hoverinfo": "none",
      "line": {
        "color": "#ff6f6f ",
        "shape": "linear",
        "width": 5.5
      },
      "mode": "lines",
      "textposition": "middle center",
      "type": "scatter",
      "x": [
        -0.567745,
        -0.896919
      ],
      "y": [
        0.880354,
        0.261847
      ]
    },
    {
      "hoverinfo": "none",
      "line": {
        "color": "#ff6f6f ",
        "shape": "linear",
        "width": 5.5
      },
      "mode": "lines",
      "textposition": "middle center",
      "type": "scatter",
      "x": [
        -0.896919,
        -0.567745
      ],
      "y": [
        0.261847,
        0.880354
      ]
    },
    {
      "hoverinfo": "none",
      "line": {
        "color": "#ff6f6f ",
        "shape": "linear",
        "width": 10.0
      },
      "mode": "lines",
      "textposition": "middle center",
      "type": "scatter",
      "x": [
        -0.567745,
        0.975852
      ],
      "y": [
        0.880354,
        -0.041317
      ]
    },
    {
      "hoverinfo": "none",
      "line": {
        "color": "#ff6f6f ",
        "shape": "linear",
        "width": 10.0
      },
      "mode": "lines",
      "textposition": "middle center",
      "type": "scatter",
      "x": [
        0.975852,
        -0.567745
      ],
      "y": [
        -0.041317,
        0.880354
      ]
    },
    {
      "hoverinfo": "none",
      "line": {
        "color": "#ff6f6f ",
        "shape": "linear",
        "width": 5.5
      },
      "mode": "lines",
      "textposition": "middle center",
      "type": "scatter",
      "x": [
        0.84436,
        0.189696
      ],
      "y": [
        0.534896,
        0.974109
      ]
    },
    {
      "hoverinfo": "none",
      "line": {
        "color": "#ff6f6f ",
        "shape": "linear",
        "width": 5.5
      },
      "mode": "lines",
      "textposition": "middle center",
      "type": "scatter",
      "x": [
        0.189696,
        0.84436
      ],
      "y": [
        0.974109,
        0.534896
      ]
    },
    {
      "hoverinfo": "none",
      "line": {
        "color": "#ff6f6f ",
        "shape": "linear",
        "width": 5.5
      },
      "mode": "lines",
      "textposition": "middle center",
      "type": "scatter",
      "x": [
        0.84436,
        0.824025
      ],
      "y": [
        0.534896,
        -0.424502
      ]
    },
    {
      "hoverinfo": "none",
      "line": {
        "color": "#ff6f6f ",
        "shape": "linear",
        "width": 5.5
      },
      "mode": "lines",
      "textposition": "middle center",
      "type": "scatter",
      "x": [
        0.824025,
        0.84436
      ],
      "y": [
        -0.424502,
        0.534896
      ]
    },
    {
      "hoverinfo": "none",
      "line": {
        "color": "#ff6f6f ",
        "shape": "linear",
        "width": 5.5
      },
      "mode": "lines",
      "textposition": "middle center",
      "type": "scatter",
      "x": [
        -0.224288,
        -1.0
      ],
      "y": [
        0.993044,
        -0.023996
      ]
    },
    {
      "hoverinfo": "none",
      "line": {
        "color": "#ff6f6f ",
        "shape": "linear",
        "width": 5.5
      },
      "mode": "lines",
      "textposition": "middle center",
      "type": "scatter",
      "x": [
        -1.0,
        -0.224288
      ],
      "y": [
        -0.023996,
        0.993044
      ]
    },
    {
      "hoverinfo": "none",
      "line": {
        "color": "#ff6f6f ",
        "shape": "linear",
        "width": 5.5
      },
      "mode": "lines",
      "textposition": "middle center",
      "type": "scatter",
      "x": [
        -0.224288,
        0.551784
      ],
      "y": [
        0.993044,
        -0.906854
      ]
    },
    {
      "hoverinfo": "none",
      "line": {
        "color": "#ff6f6f ",
        "shape": "linear",
        "width": 5.5
      },
      "mode": "lines",
      "textposition": "middle center",
      "type": "scatter",
      "x": [
        0.551784,
        -0.224288
      ],
      "y": [
        -0.906854,
        0.993044
      ]
    },
    {
      "hoverinfo": "none",
      "line": {
        "color": "#ff6f6f ",
        "shape": "linear",
        "width": 5.5
      },
      "mode": "lines",
      "textposition": "middle center",
      "type": "scatter",
      "x": [
        0.384572,
        0.939291
      ],
      "y": [
        -0.72715,
        -0.464783
      ]
    },
    {
      "hoverinfo": "none",
      "line": {
        "color": "#ff6f6f ",
        "shape": "linear",
        "width": 5.5
      },
      "mode": "lines",
      "textposition": "middle center",
      "type": "scatter",
      "x": [
        0.939291,
        0.384572
      ],
      "y": [
        -0.464783,
        -0.72715
      ]
    },
    {
      "hoverinfo": "none",
      "line": {
        "color": "#ff6f6f ",
        "shape": "linear",
        "width": 5.5
      },
      "mode": "lines",
      "textposition": "middle center",
      "type": "scatter",
      "x": [
        0.551784,
        0.226417
      ],
      "y": [
        -0.906854,
        -0.991429
      ]
    },
    {
      "hoverinfo": "none",
      "line": {
        "color": "#ff6f6f ",
        "shape": "linear",
        "width": 5.5
      },
      "mode": "lines",
      "textposition": "middle center",
      "type": "scatter",
      "x": [
        0.226417,
        0.551784
      ],
      "y": [
        -0.991429,
        -0.906854
      ]
    },
    {
      "hoverinfo": "none",
      "line": {
        "color": "#ff6f6f ",
        "shape": "linear",
        "width": 5.5
      },
      "mode": "lines",
      "textposition": "middle center",
      "type": "scatter",
      "x": [
        -0.607724,
        0.83102
      ],
      "y": [
        -0.568064,
        -0.540672
      ]
    },
    {
      "hoverinfo": "none",
      "line": {
        "color": "#ff6f6f ",
        "shape": "linear",
        "width": 5.5
      },
      "mode": "lines",
      "textposition": "middle center",
      "type": "scatter",
      "x": [
        0.83102,
        -0.607724
      ],
      "y": [
        -0.540672,
        -0.568064
      ]
    },
    {
      "hoverinfo": "text",
      "hovertext": [
        "<b>AS1</b><br>Ventral cord motor neuron",
        "<b>AS10</b><br>Ventral cord motor neuron",
        "<b>AS11</b><br>Ventral cord motor neuron",
        "<b>AS2</b><br>Ventral cord motor neuron",
        "<b>AS3</b><br>Ventral cord motor neuron",
        "<b>AS4</b><br>Ventral cord motor neuron",
        "<b>AS5</b><br>Ventral cord motor neuron",
        "<b>AS6</b><br>Ventral cord motor neuron",
        "<b>AS7</b><br>Ventral cord motor neuron",
        "<b>AS8</b><br>Ventral cord motor neuron",
        "<b>AS9</b><br>Ventral cord motor neuron",
        "<b>DA1</b><br>Ventral cord motor neuron",
        "<b>DA2</b><br>Ventral cord motor neuron",
        "<b>DA3</b><br>Ventral cord motor neuron",
        "<b>DA4</b><br>Ventral cord motor neuron",
        "<b>DA5</b><br>Ventral cord motor neuron",
        "<b>DA6</b><br>Ventral cord motor neuron",
        "<b>DA7</b><br>Ventral cord motor neuron",
        "<b>DA8</b><br>Ventral cord motor neuron",
        "<b>DA9</b><br>Ventral cord motor neuron",
        "<b>DB1</b><br>Ventral cord motor neuron",
        "<b>DB2</b><br>Ventral cord motor neuron",
        "<b>DB3</b><br>Ventral cord motor neuron",
        "<b>DB4</b><br>Ventral cord motor neuron",
        "<b>DB5</b><br>Ventral cord motor neuron",
        "<b>DB6</b><br>Ventral cord motor neuron",
        "<b>DB7</b><br>Ventral cord motor neuron",
        "<b>DD1</b><br>Ventral cord motor neuron",
        "<b>DD2</b><br>Ventral cord motor neuron",
        "<b>DD3</b><br>Ventral cord motor neuron",
        "<b>DD4</b><br>Ventral cord motor neuron",
        "<b>DD5</b><br>Ventral cord motor neuron",
        "<b>DD6</b><br>Ventral cord motor neuron",
        "<b>HSNL</b><br>Hermaphrodite specific motor neuron",
        "<b>HSNR</b><br>Hermaphrodite specific motor neuron",
        "<b>PDA</b><br>Ventral cord motor neuron",
        "<b>PDB</b><br>Ventral cord motor neuron",
        "<b>RIVL</b><br>Head motor neuron<br>Conns in: <b>RIVR</b>: 1, <b>SMDDR</b>: 1<br>Conns out: <b>RIVR</b>: 1, <b>SMDDR</b>: 1",
        "<b>RIVR</b><br>Head motor neuron<br>Conns in: <b>RIVL</b>: 1<br>Conns out: <b>RIVL</b>: 1",
        "<b>RMDDL</b><br>Head motor neuron<br>Conns in: <b>RMDL</b>: 1, <b>RMDR</b>: 1, <b>SMDDL</b>: 1, <b>SMDVR</b>: 1<br>Conns out: <b>RMDL</b>: 1, <b>RMDR</b>: 1, <b>SMDDL</b>: 1, <b>SMDVR</b>: 1",
        "<b>RMDDR</b><br>Head motor neuron<br>Conns in: <b>RMDR</b>: 1, <b>RMDVR</b>: 1, <b>SIAVL</b>: 1, <b>SIBVL</b>: 1, <b>SMDDR</b>: 1, <br><b>SMDVL</b>: 1<br>Conns out: <b>RMDR</b>: 1, <b>RMDVR</b>: 1, <b>SIAVL</b>: 1, <b>SIBVL</b>: 1, <b>SMDDR</b>: 1, <br><b>SMDVL</b>: 1",
        "<b>RMDL</b><br>Head motor neuron<br>Conns in: <b>RMDDL</b>: 1, <b>RMDVL</b>: 1, <b>SMDVL</b>: 1<br>Conns out: <b>RMDDL</b>: 1, <b>RMDVL</b>: 1, <b>SMDVL</b>: 1",
        "<b>RMDR</b><br>Head motor neuron<br>Conns in: <b>RMDDL</b>: 1, <b>RMDDR</b>: 1, <b>RMDVR</b>: 1<br>Conns out: <b>RMDDL</b>: 1, <b>RMDDR</b>: 1, <b>RMDVR</b>: 1",
        "<b>RMDVL</b><br>Head motor neuron<br>Conns in: <b>SMDVL</b>: 2, <b>RMDL</b>: 1, <b>RMHR</b>: 1, <b>SIAVR</b>: 1<br>Conns out: <b>SMDVL</b>: 2, <b>RMDL</b>: 1, <b>RMHR</b>: 1, <b>SIAVR</b>: 1",
        "<b>RMDVR</b><br>Head motor neuron<br>Conns in: <b>RMDDR</b>: 1, <b>RMDR</b>: 1, <b>RMHR</b>: 1, <b>SMDVR</b>: 1<br>Conns out: <b>RMDDR</b>: 1, <b>RMDR</b>: 1, <b>RMHR</b>: 1, <b>SMDVR</b>: 1",
        "<b>RMED</b><br>Head motor neuron",
        "<b>RMEL</b><br>Head motor neuron",
        "<b>RMER</b><br>Head motor neuron",
        "<b>RMEV</b><br>Head motor neuron",
        "<b>RMHL</b><br>Head motor neuron",
        "<b>RMHR</b><br>Head motor neuron<br>Conns in: <b>RMDVL</b>: 1, <b>RMDVR</b>: 1<br>Conns out: <b>RMDVL</b>: 1, <b>RMDVR</b>: 1",
        "<b>SABD</b><br>Sublateral motor neuron; interneuron in White et al., 1986",
        "<b>SABVL</b><br>Sublateral motor neuron; interneuron in White et al., 1986",
        "<b>SABVR</b><br>Sublateral motor neuron; interneuron in White et al., 1986",
        "<b>SIADL</b><br>Sublateral motor neuron; interneuron in White et al., 1986",
        "<b>SIADR</b><br>Sublateral motor neuron; interneuron in White et al., 1986",
        "<b>SIAVL</b><br>Sublateral motor neuron; interneuron in White et al., 1986<br>Conns in: <b>RMDDR</b>: 1<br>Conns out: <b>RMDDR</b>: 1",
        "<b>SIAVR</b><br>Sublateral motor neuron; interneuron in White et al., 1986<br>Conns in: <b>RMDVL</b>: 1<br>Conns out: <b>RMDVL</b>: 1",
        "<b>SIBDL</b><br>Sublateral motor neuron; interneuron in White et al., 1986<br>Conns in: <b>SIBVL</b>: 1, <b>SMBDL</b>: 1<br>Conns out: <b>SIBVL</b>: 1, <b>SMBDL</b>: 1",
        "<b>SIBDR</b><br>Sublateral motor neuron; interneuron in White et al., 1986<br>Conns in: <b>SIBVR</b>: 1<br>Conns out: <b>SIBVR</b>: 1",
        "<b>SIBVL</b><br>Sublateral motor neuron; interneuron in White et al., 1986<br>Conns in: <b>RMDDR</b>: 1, <b>SIBDL</b>: 1<br>Conns out: <b>RMDDR</b>: 1, <b>SIBDL</b>: 1",
        "<b>SIBVR</b><br>Sublateral motor neuron; interneuron in White et al., 1986<br>Conns in: <b>SIBDR</b>: 1<br>Conns out: <b>SIBDR</b>: 1",
        "<b>SMBDL</b><br>Sublateral motor neuron<br>Conns in: <b>SIBDL</b>: 1, <b>SMBDR</b>: 1<br>Conns out: <b>SIBDL</b>: 1, <b>SMBDR</b>: 1",
        "<b>SMBDR</b><br>Sublateral motor neuron<br>Conns in: <b>SMBDL</b>: 1<br>Conns out: <b>SMBDL</b>: 1",
        "<b>SMBVL</b><br>Sublateral motor neuron",
        "<b>SMBVR</b><br>Sublateral motor neuron",
        "<b>SMDDL</b><br>Sublateral motor neuron<br>Conns in: <b>RMDDL</b>: 1, <b>SMDDR</b>: 1<br>Conns out: <b>RMDDL</b>: 1, <b>SMDDR</b>: 1",
        "<b>SMDDR</b><br>Sublateral motor neuron<br>Conns in: <b>RIVL</b>: 1, <b>RMDDR</b>: 1, <b>SMDDL</b>: 1<br>Conns out: <b>RIVL</b>: 1, <b>RMDDR</b>: 1, <b>SMDDL</b>: 1",
        "<b>SMDVL</b><br>Sublateral motor neuron<br>Conns in: <b>RMDVL</b>: 2, <b>RMDDR</b>: 1, <b>RMDL</b>: 1<br>Conns out: <b>RMDVL</b>: 2, <b>RMDDR</b>: 1, <b>RMDL</b>: 1",
        "<b>SMDVR</b><br>Sublateral motor neuron<br>Conns in: <b>RMDDL</b>: 1, <b>RMDVR</b>: 1<br>Conns out: <b>RMDDL</b>: 1, <b>RMDVR</b>: 1",
        "<b>URADL</b><br>Head motor neuron",
        "<b>URADR</b><br>Head motor neuron",
        "<b>URAVL</b><br>Head motor neuron",
        "<b>URAVR</b><br>Head motor neuron",
        "<b>VA1</b><br>Ventral cord motor neuron",
        "<b>VA10</b><br>Ventral cord motor neuron",
        "<b>VA11</b><br>Ventral cord motor neuron",
        "<b>VA12</b><br>Ventral cord motor neuron",
        "<b>VA2</b><br>Ventral cord motor neuron",
        "<b>VA3</b><br>Ventral cord motor neuron",
        "<b>VA4</b><br>Ventral cord motor neuron",
        "<b>VA5</b><br>Ventral cord motor neuron",
        "<b>VA6</b><br>Ventral cord motor neuron",
        "<b>VA7</b><br>Ventral cord motor neuron",
        "<b>VA8</b><br>Ventral cord motor neuron",
        "<b>VA9</b><br>Ventral cord motor neuron",
        "<b>VB1</b><br>Ventral cord motor neuron",
        "<b>VB10</b><br>Ventral cord motor neuron",
        "<b>VB11</b><br>Ventral cord motor neuron",
        "<b>VB2</b><br>Ventral cord motor neuron",
        "<b>VB3</b><br>Ventral cord motor neuron",
        "<b>VB4</b><br>Ventral cord motor neuron",
        "<b>VB5</b><br>Ventral cord motor neuron",
        "<b>VB6</b><br>Ventral cord motor neuron",
        "<b>VB7</b><br>Ventral cord motor neuron",
        "<b>VB8</b><br>Ventral cord motor neuron",
        "<b>VB9</b><br>Ventral cord motor neuron",
        "<b>VC1</b><br>Hermaphrodite specific motor neuron",
        "<b>VC2</b><br>Hermaphrodite specific motor neuron",
        "<b>VC3</b><br>Hermaphrodite specific motor neuron",
        "<b>VC4</b><br>Hermaphrodite specific motor neuron",
        "<b>VC5</b><br>Hermaphrodite specific motor neuron",
        "<b>VC6</b><br>Hermaphrodite specific motor neuron",
        "<b>VD1</b><br>Ventral cord motor neuron",
        "<b>VD10</b><br>Ventral cord motor neuron",
        "<b>VD11</b><br>Ventral cord motor neuron",
        "<b>VD12</b><br>Ventral cord motor neuron",
        "<b>VD13</b><br>Ventral cord motor neuron",
        "<b>VD2</b><br>Ventral cord motor neuron",
        "<b>VD3</b><br>Ventral cord motor neuron",
        "<b>VD4</b><br>Ventral cord motor neuron",
        "<b>VD5</b><br>Ventral cord motor neuron",
        "<b>VD6</b><br>Ventral cord motor neuron",
        "<b>VD7</b><br>Ventral cord motor neuron",
        "<b>VD8</b><br>Ventral cord motor neuron",
        "<b>VD9</b><br>Ventral cord motor neuron"
      ],
      "marker": {
        "color": [
          "#9966cc",
          "#9966cc",
          "#9966cc",
          "#9966cc",
          "#9966cc",
          "#9966cc",
          "#9966cc",
          "#9966cc",
          "#9966cc",
          "#9966cc",
          "#9966cc",
          "#9966cc",
          "#9966cc",
          "#9966cc",
          "#9966cc",
          "#9966cc",
          "#9966cc",
          "#9966cc",
          "#9966cc",
          "#9966cc",
          "#9966cc",
          "#9966cc",
          "#9966cc",
          "#9966cc",
          "#9966cc",
          "#9966cc",
          "#9966cc",
          "#9966cc",
          "#9966cc",
          "#9966cc",
          "#9966cc",
          "#9966cc",
          "#9966cc",
          "#9966cc",
          "#9966cc",
          "#9966cc",
          "#9966cc",
          "#9966cc",
          "#9966cc",
          "#9966cc",
          "#9966cc",
          "#9966cc",
          "#9966cc",
          "#9966cc",
          "#9966cc",
          "#9966cc",
          "#9966cc",
          "#9966cc",
          "#9966cc",
          "#9966cc",
          "#9966cc",
          "#9966cc",
          "#9966cc",
          "#9966cc",
          "#9966cc",
          "#9966cc",
          "#9966cc",
          "#9966cc",
          "#9966cc",
          "#9966cc",
          "#9966cc",
          "#9966cc",
          "#9966cc",
          "#9966cc",
          "#9966cc",
          "#9966cc",
          "#9966cc",
          "#9966cc",
          "#9966cc",
          "#9966cc",
          "#9966cc",
          "#9966cc",
          "#9966cc",
          "#9966cc",
          "#9966cc",
          "#9966cc",
          "#9966cc",
          "#9966cc",
          "#9966cc",
          "#9966cc",
          "#9966cc",
          "#9966cc",
          "#9966cc",
          "#9966cc",
          "#9966cc",
          "#9966cc",
          "#9966cc",
          "#9966cc",
          "#9966cc",
          "#9966cc",
          "#9966cc",
          "#9966cc",
          "#9966cc",
          "#9966cc",
          "#9966cc",
          "#9966cc",
          "#9966cc",
          "#9966cc",
          "#9966cc",
          "#9966cc",
          "#9966cc",
          "#9966cc",
          "#9966cc",
          "#9966cc",
          "#9966cc",
          "#9966cc",
          "#9966cc",
          "#9966cc",
          "#9966cc",
          "#9966cc",
          "#9966cc",
          "#9966cc",
          "#9966cc",
          "#9966cc",
          "#9966cc",
          "#9966cc"
        ],
        "colorbar": {
          "thickness": 15,
          "title": {
            "text": "Node Connections"
          },
          "xanchor": "left"
        },
        "colorscale": [
          [
            0.0,
            "rgb(255,255,217)"
          ],
          [
            0.125,
            "rgb(237,248,177)"
          ],
          [
            0.25,
            "rgb(199,233,180)"
          ],
          [
            0.375,
            "rgb(127,205,187)"
          ],
          [
            0.5,
            "rgb(65,182,196)"
          ],
          [
            0.625,
            "rgb(29,145,192)"
          ],
          [
            0.75,
            "rgb(34,94,168)"
          ],
          [
            0.875,
            "rgb(37,52,148)"
          ],
          [
            1.0,
            "rgb(8,29,88)"
          ]
        ],
        "line": {
          "width": 1
        },
        "reversescale": true,
        "showscale": false,
        "size": [
          15.0,
          15.0,
          15.0,
          15.0,
          15.0,
          15.0,
          15.0,
          15.0,
          15.0,
          15.0,
          15.0,
          15.0,
          15.0,
          15.0,
          15.0,
          15.0,
          15.0,
          15.0,
          15.0,
          15.0,
          15.0,
          15.0,
          15.0,
          15.0,
          15.0,
          15.0,
          15.0,
          15.0,
          15.0,
          15.0,
          15.0,
          15.0,
          15.0,
          15.0,
          15.0,
          15.0,
          15.0,
          15.0,
          15.0,
          15.0,
          15.0,
          15.0,
          15.0,
          15.0,
          15.0,
          15.0,
          15.0,
          15.0,
          15.0,
          15.0,
          15.0,
          15.0,
          15.0,
          15.0,
          15.0,
          15.0,
          15.0,
          15.0,
          15.0,
          15.0,
          15.0,
          15.0,
          15.0,
          15.0,
          15.0,
          15.0,
          15.0,
          15.0,
          15.0,
          15.0,
          15.0,
          15.0,
          15.0,
          15.0,
          15.0,
          15.0,
          15.0,
          15.0,
          15.0,
          15.0,
          15.0,
          15.0,
          15.0,
          15.0,
          15.0,
          15.0,
          15.0,
          15.0,
          15.0,
          15.0,
          15.0,
          15.0,
          15.0,
          15.0,
          15.0,
          15.0,
          15.0,
          15.0,
          15.0,
          15.0,
          15.0,
          15.0,
          15.0,
          15.0,
          15.0,
          15.0,
          15.0,
          15.0,
          15.0,
          15.0,
          15.0,
          15.0,
          15.0,
          15.0,
          15.0,
          15.0
        ],
        "symbol": [
          "circle",
          "circle",
          "circle",
          "circle",
          "circle",
          "circle",
          "circle",
          "circle",
          "circle",
          "circle",
          "circle",
          "circle",
          "circle",
          "circle",
          "circle",
          "circle",
          "circle",
          "circle",
          "circle",
          "circle",
          "circle",
          "circle",
          "circle",
          "circle",
          "circle",
          "circle",
          "circle",
          "circle",
          "circle",
          "circle",
          "circle",
          "circle",
          "circle",
          "circle",
          "circle",
          "circle",
          "circle",
          "circle",
          "circle",
          "circle",
          "circle",
          "circle",
          "circle",
          "circle",
          "circle",
          "circle",
          "circle",
          "circle",
          "circle",
          "circle",
          "circle",
          "circle",
          "circle",
          "circle",
          "circle",
          "circle",
          "circle",
          "circle",
          "circle",
          "circle",
          "circle",
          "circle",
          "circle",
          "circle",
          "circle",
          "circle",
          "circle",
          "circle",
          "circle",
          "circle",
          "circle",
          "circle",
          "circle",
          "circle",
          "circle",
          "circle",
          "circle",
          "circle",
          "circle",
          "circle",
          "circle",
          "circle",
          "circle",
          "circle",
          "circle",
          "circle",
          "circle",
          "circle",
          "circle",
          "circle",
          "circle",
          "circle",
          "circle",
          "circle",
          "circle",
          "circle",
          "circle",
          "circle",
          "circle",
          "circle",
          "circle",
          "circle",
          "circle",
          "circle",
          "circle",
          "circle",
          "circle",
          "circle",
          "circle",
          "circle",
          "circle",
          "circle",
          "circle",
          "circle",
          "circle",
          "circle"
        ]
      },
      "mode": "markers",
      "opacity": 1,
      "text": [
        "<span style=\"color:#000000;font-size:1.0em\"><b>AS1</b></span>",
        "<span style=\"color:#000000;font-size:1.0em\"><b>AS10</b></span>",
        "<span style=\"color:#000000;font-size:1.0em\"><b>AS11</b></span>",
        "<span style=\"color:#000000;font-size:1.0em\"><b>AS2</b></span>",
        "<span style=\"color:#000000;font-size:1.0em\"><b>AS3</b></span>",
        "<span style=\"color:#000000;font-size:1.0em\"><b>AS4</b></span>",
        "<span style=\"color:#000000;font-size:1.0em\"><b>AS5</b></span>",
        "<span style=\"color:#000000;font-size:1.0em\"><b>AS6</b></span>",
        "<span style=\"color:#000000;font-size:1.0em\"><b>AS7</b></span>",
        "<span style=\"color:#000000;font-size:1.0em\"><b>AS8</b></span>",
        "<span style=\"color:#000000;font-size:1.0em\"><b>AS9</b></span>",
        "<span style=\"color:#000000;font-size:1.0em\"><b>DA1</b></span>",
        "<span style=\"color:#000000;font-size:1.0em\"><b>DA2</b></span>",
        "<span style=\"color:#000000;font-size:1.0em\"><b>DA3</b></span>",
        "<span style=\"color:#000000;font-size:1.0em\"><b>DA4</b></span>",
        "<span style=\"color:#000000;font-size:1.0em\"><b>DA5</b></span>",
        "<span style=\"color:#000000;font-size:1.0em\"><b>DA6</b></span>",
        "<span style=\"color:#000000;font-size:1.0em\"><b>DA7</b></span>",
        "<span style=\"color:#000000;font-size:1.0em\"><b>DA8</b></span>",
        "<span style=\"color:#000000;font-size:1.0em\"><b>DA9</b></span>",
        "<span style=\"color:#000000;font-size:1.0em\"><b>DB1</b></span>",
        "<span style=\"color:#000000;font-size:1.0em\"><b>DB2</b></span>",
        "<span style=\"color:#000000;font-size:1.0em\"><b>DB3</b></span>",
        "<span style=\"color:#000000;font-size:1.0em\"><b>DB4</b></span>",
        "<span style=\"color:#000000;font-size:1.0em\"><b>DB5</b></span>",
        "<span style=\"color:#000000;font-size:1.0em\"><b>DB6</b></span>",
        "<span style=\"color:#000000;font-size:1.0em\"><b>DB7</b></span>",
        "<span style=\"color:#000000;font-size:1.0em\"><b>DD1</b></span>",
        "<span style=\"color:#000000;font-size:1.0em\"><b>DD2</b></span>",
        "<span style=\"color:#000000;font-size:1.0em\"><b>DD3</b></span>",
        "<span style=\"color:#000000;font-size:1.0em\"><b>DD4</b></span>",
        "<span style=\"color:#000000;font-size:1.0em\"><b>DD5</b></span>",
        "<span style=\"color:#000000;font-size:1.0em\"><b>DD6</b></span>",
        "<span style=\"color:#000000;font-size:1.0em\"><b>HSNL</b></span>",
        "<span style=\"color:#000000;font-size:1.0em\"><b>HSNR</b></span>",
        "<span style=\"color:#000000;font-size:1.0em\"><b>PDA</b></span>",
        "<span style=\"color:#000000;font-size:1.0em\"><b>PDB</b></span>",
        "<span style=\"color:#000000;font-size:1.0em\"><b>RIVL</b></span>",
        "<span style=\"color:#000000;font-size:1.0em\"><b>RIVR</b></span>",
        "<span style=\"color:#000000;font-size:1.0em\"><b>RMDDL</b></span>",
        "<span style=\"color:#000000;font-size:1.0em\"><b>RMDDR</b></span>",
        "<span style=\"color:#000000;font-size:1.0em\"><b>RMDL</b></span>",
        "<span style=\"color:#000000;font-size:1.0em\"><b>RMDR</b></span>",
        "<span style=\"color:#000000;font-size:1.0em\"><b>RMDVL</b></span>",
        "<span style=\"color:#000000;font-size:1.0em\"><b>RMDVR</b></span>",
        "<span style=\"color:#000000;font-size:1.0em\"><b>RMED</b></span>",
        "<span style=\"color:#000000;font-size:1.0em\"><b>RMEL</b></span>",
        "<span style=\"color:#000000;font-size:1.0em\"><b>RMER</b></span>",
        "<span style=\"color:#000000;font-size:1.0em\"><b>RMEV</b></span>",
        "<span style=\"color:#000000;font-size:1.0em\"><b>RMHL</b></span>",
        "<span style=\"color:#000000;font-size:1.0em\"><b>RMHR</b></span>",
        "<span style=\"color:#000000;font-size:1.0em\"><b>SABD</b></span>",
        "<span style=\"color:#000000;font-size:1.0em\"><b>SABVL</b></span>",
        "<span style=\"color:#000000;font-size:1.0em\"><b>SABVR</b></span>",
        "<span style=\"color:#000000;font-size:1.0em\"><b>SIADL</b></span>",
        "<span style=\"color:#000000;font-size:1.0em\"><b>SIADR</b></span>",
        "<span style=\"color:#000000;font-size:1.0em\"><b>SIAVL</b></span>",
        "<span style=\"color:#000000;font-size:1.0em\"><b>SIAVR</b></span>",
        "<span style=\"color:#000000;font-size:1.0em\"><b>SIBDL</b></span>",
        "<span style=\"color:#000000;font-size:1.0em\"><b>SIBDR</b></span>",
        "<span style=\"color:#000000;font-size:1.0em\"><b>SIBVL</b></span>",
        "<span style=\"color:#000000;font-size:1.0em\"><b>SIBVR</b></span>",
        "<span style=\"color:#000000;font-size:1.0em\"><b>SMBDL</b></span>",
        "<span style=\"color:#000000;font-size:1.0em\"><b>SMBDR</b></span>",
        "<span style=\"color:#000000;font-size:1.0em\"><b>SMBVL</b></span>",
        "<span style=\"color:#000000;font-size:1.0em\"><b>SMBVR</b></span>",
        "<span style=\"color:#000000;font-size:1.0em\"><b>SMDDL</b></span>",
        "<span style=\"color:#000000;font-size:1.0em\"><b>SMDDR</b></span>",
        "<span style=\"color:#000000;font-size:1.0em\"><b>SMDVL</b></span>",
        "<span style=\"color:#000000;font-size:1.0em\"><b>SMDVR</b></span>",
        "<span style=\"color:#000000;font-size:1.0em\"><b>URADL</b></span>",
        "<span style=\"color:#000000;font-size:1.0em\"><b>URADR</b></span>",
        "<span style=\"color:#000000;font-size:1.0em\"><b>URAVL</b></span>",
        "<span style=\"color:#000000;font-size:1.0em\"><b>URAVR</b></span>",
        "<span style=\"color:#000000;font-size:1.0em\"><b>VA1</b></span>",
        "<span style=\"color:#000000;font-size:1.0em\"><b>VA10</b></span>",
        "<span style=\"color:#000000;font-size:1.0em\"><b>VA11</b></span>",
        "<span style=\"color:#000000;font-size:1.0em\"><b>VA12</b></span>",
        "<span style=\"color:#000000;font-size:1.0em\"><b>VA2</b></span>",
        "<span style=\"color:#000000;font-size:1.0em\"><b>VA3</b></span>",
        "<span style=\"color:#000000;font-size:1.0em\"><b>VA4</b></span>",
        "<span style=\"color:#000000;font-size:1.0em\"><b>VA5</b></span>",
        "<span style=\"color:#000000;font-size:1.0em\"><b>VA6</b></span>",
        "<span style=\"color:#000000;font-size:1.0em\"><b>VA7</b></span>",
        "<span style=\"color:#000000;font-size:1.0em\"><b>VA8</b></span>",
        "<span style=\"color:#000000;font-size:1.0em\"><b>VA9</b></span>",
        "<span style=\"color:#000000;font-size:1.0em\"><b>VB1</b></span>",
        "<span style=\"color:#000000;font-size:1.0em\"><b>VB10</b></span>",
        "<span style=\"color:#000000;font-size:1.0em\"><b>VB11</b></span>",
        "<span style=\"color:#000000;font-size:1.0em\"><b>VB2</b></span>",
        "<span style=\"color:#000000;font-size:1.0em\"><b>VB3</b></span>",
        "<span style=\"color:#000000;font-size:1.0em\"><b>VB4</b></span>",
        "<span style=\"color:#000000;font-size:1.0em\"><b>VB5</b></span>",
        "<span style=\"color:#000000;font-size:1.0em\"><b>VB6</b></span>",
        "<span style=\"color:#000000;font-size:1.0em\"><b>VB7</b></span>",
        "<span style=\"color:#000000;font-size:1.0em\"><b>VB8</b></span>",
        "<span style=\"color:#000000;font-size:1.0em\"><b>VB9</b></span>",
        "<span style=\"color:#000000;font-size:1.0em\"><b>VC1</b></span>",
        "<span style=\"color:#000000;font-size:1.0em\"><b>VC2</b></span>",
        "<span style=\"color:#000000;font-size:1.0em\"><b>VC3</b></span>",
        "<span style=\"color:#000000;font-size:1.0em\"><b>VC4</b></span>",
        "<span style=\"color:#000000;font-size:1.0em\"><b>VC5</b></span>",
        "<span style=\"color:#000000;font-size:1.0em\"><b>VC6</b></span>",
        "<span style=\"color:#000000;font-size:1.0em\"><b>VD1</b></span>",
        "<span style=\"color:#000000;font-size:1.0em\"><b>VD10</b></span>",
        "<span style=\"color:#000000;font-size:1.0em\"><b>VD11</b></span>",
        "<span style=\"color:#000000;font-size:1.0em\"><b>VD12</b></span>",
        "<span style=\"color:#000000;font-size:1.0em\"><b>VD13</b></span>",
        "<span style=\"color:#000000;font-size:1.0em\"><b>VD2</b></span>",
        "<span style=\"color:#000000;font-size:1.0em\"><b>VD3</b></span>",
        "<span style=\"color:#000000;font-size:1.0em\"><b>VD4</b></span>",
        "<span style=\"color:#000000;font-size:1.0em\"><b>VD5</b></span>",
        "<span style=\"color:#000000;font-size:1.0em\"><b>VD6</b></span>",
        "<span style=\"color:#000000;font-size:1.0em\"><b>VD7</b></span>",
        "<span style=\"color:#000000;font-size:1.0em\"><b>VD8</b></span>",
        "<span style=\"color:#000000;font-size:1.0em\"><b>VD9</b></span>"
      ],
      "textposition": "middle center",
      "type": "scatter",
      "x": [
        -0.094436,
        0.873423,
        -0.63437,
        0.116945,
        0.554544,
        -0.149146,
        0.693235,
        -0.356362,
        0.887779,
        -0.332085,
        -0.083361,
        0.394411,
        0.299438,
        0.509894,
        0.666388,
        -0.077372,
        -0.900936,
        0.681158,
        -0.655274,
        0.979934,
        0.630837,
        0.747346,
        -0.771523,
        -0.953654,
        -0.025931,
        0.410845,
        0.089437,
        0.760791,
        -0.240335,
        -0.053527,
        0.560326,
        -0.979198,
        0.971845,
        0.812451,
        0.080775,
        -0.469267,
        0.7459,
        -0.373632,
        0.404669,
        0.785876,
        -0.633697,
        0.873495,
        0.857336,
        -0.567745,
        0.84436,
        -0.705259,
        -0.893338,
        -0.768329,
        0.913651,
        -0.887309,
        0.189696,
        -0.81291,
        -0.774113,
        -0.884441,
        0.530558,
        -0.809251,
        0.935388,
        -0.896919,
        -0.224288,
        0.384572,
        -1.0,
        0.939291,
        0.551784,
        0.226417,
        0.86192,
        0.658083,
        -0.607724,
        0.83102,
        0.975852,
        0.824025,
        -0.222677,
        -0.714176,
        -0.319445,
        0.4425,
        0.597468,
        0.88368,
        0.29195,
        -0.899465,
        -0.931556,
        -0.747415,
        -0.44562,
        0.866052,
        -0.899264,
        0.268614,
        -0.793552,
        -0.577929,
        -0.854995,
        0.974955,
        -0.465994,
        -0.96912,
        -0.825113,
        0.017329,
        -0.115519,
        -0.200439,
        -0.594201,
        0.184597,
        0.756244,
        0.377694,
        0.780948,
        0.562824,
        -0.375257,
        0.719732,
        -0.326644,
        -0.96765,
        -0.743676,
        -0.902164,
        0.938952,
        -0.557561,
        -0.646805,
        0.290465,
        0.150727,
        -0.908334,
        0.57604,
        -0.717251,
        0.075333,
        -0.474251
      ],
      "y": [
        -0.92717,
        0.327938,
        0.636942,
        0.871582,
        -0.682015,
        0.961997,
        -0.633481,
        -0.69822,
        -0.341954,
        -0.822524,
        0.798491,
        0.949963,
        -0.923305,
        0.889796,
        0.666513,
        -0.991465,
        0.464032,
        0.449617,
        -0.67424,
        -0.153183,
        0.80678,
        0.490306,
        -0.549091,
        0.159148,
        0.926576,
        0.737358,
        -0.918395,
        0.596669,
        0.795219,
        0.996819,
        -0.485971,
        0.065396,
        0.084796,
        0.118908,
        0.956228,
        0.733997,
        -0.809167,
        0.912747,
        -0.929351,
        -0.230606,
        -0.419642,
        -0.622643,
        0.23011,
        0.880354,
        0.534896,
        0.474497,
        -0.109504,
        0.298368,
        0.082934,
        -0.592681,
        0.974109,
        -0.317971,
        -0.682383,
        0.130926,
        0.729068,
        0.692994,
        0.353421,
        0.261847,
        0.993044,
        -0.72715,
        -0.023996,
        -0.464783,
        -0.906854,
        -0.991429,
        0.437207,
        -0.774321,
        -0.568064,
        -0.540672,
        -0.041317,
        -0.424502,
        -0.873969,
        0.758032,
        0.9733,
        -0.854639,
        0.768559,
        -0.168346,
        0.943692,
        0.627825,
        -0.341377,
        0.569952,
        -0.853785,
        -0.042648,
        -0.23853,
        -0.850681,
        -0.168769,
        -0.896142,
        0.009086,
        0.214014,
        -0.732099,
        -0.135306,
        0.473947,
        -0.955081,
        -0.694382,
        -0.937077,
        0.806146,
        0.792986,
        0.691136,
        0.849624,
        -0.695583,
        -0.830138,
        0.838391,
        -0.447032,
        -0.928891,
        0.278268,
        -0.414193,
        -0.462592,
        -0.263323,
        -0.72703,
        0.716205,
        0.684742,
        -0.961069,
        0.36805,
        0.303022,
        -0.823248,
        -0.782834,
        0.918237
      ]
    }
  ],
  "layout": {
    "height": 800,
    "hovermode": "closest",
    "margin": {
      "b": 20,
      "l": 5,
      "r": 5,
      "t": 40
    },
    "showlegend": false,
    "template": {
      "data": {
        "bar": [
          {
            "error_x": {
              "color": "#2a3f5f"
            },
            "error_y": {
              "color": "#2a3f5f"
            },
            "marker": {
              "line": {
                "color": "white",
                "width": 0.5
              },
              "pattern": {
                "fillmode": "overlay",
                "size": 10,
                "solidity": 0.2
              }
            },
            "type": "bar"
          }
        ],
        "barpolar": [
          {
            "marker": {
              "line": {
                "color": "white",
                "width": 0.5
              },
              "pattern": {
                "fillmode": "overlay",
                "size": 10,
                "solidity": 0.2
              }
            },
            "type": "barpolar"
          }
        ],
        "carpet": [
          {
            "aaxis": {
              "endlinecolor": "#2a3f5f",
              "gridcolor": "#C8D4E3",
              "linecolor": "#C8D4E3",
              "minorgridcolor": "#C8D4E3",
              "startlinecolor": "#2a3f5f"
            },
            "baxis": {
              "endlinecolor": "#2a3f5f",
              "gridcolor": "#C8D4E3",
              "linecolor": "#C8D4E3",
              "minorgridcolor": "#C8D4E3",
              "startlinecolor": "#2a3f5f"
            },
            "type": "carpet"
          }
        ],
        "choropleth": [
          {
            "colorbar": {
              "outlinewidth": 0,
              "ticks": ""
            },
            "type": "choropleth"
          }
        ],
        "contour": [
          {
            "colorbar": {
              "outlinewidth": 0,
              "ticks": ""
            },
            "colorscale": [
              [
                0.0,
                "#0d0887"
              ],
              [
                0.1111111111111111,
                "#46039f"
              ],
              [
                0.2222222222222222,
                "#7201a8"
              ],
              [
                0.3333333333333333,
                "#9c179e"
              ],
              [
                0.4444444444444444,
                "#bd3786"
              ],
              [
                0.5555555555555556,
                "#d8576b"
              ],
              [
                0.6666666666666666,
                "#ed7953"
              ],
              [
                0.7777777777777778,
                "#fb9f3a"
              ],
              [
                0.8888888888888888,
                "#fdca26"
              ],
              [
                1.0,
                "#f0f921"
              ]
            ],
            "type": "contour"
          }
        ],
        "contourcarpet": [
          {
            "colorbar": {
              "outlinewidth": 0,
              "ticks": ""
            },
            "type": "contourcarpet"
          }
        ],
        "heatmap": [
          {
            "colorbar": {
              "outlinewidth": 0,
              "ticks": ""
            },
            "colorscale": [
              [
                0.0,
                "#0d0887"
              ],
              [
                0.1111111111111111,
                "#46039f"
              ],
              [
                0.2222222222222222,
                "#7201a8"
              ],
              [
                0.3333333333333333,
                "#9c179e"
              ],
              [
                0.4444444444444444,
                "#bd3786"
              ],
              [
                0.5555555555555556,
                "#d8576b"
              ],
              [
                0.6666666666666666,
                "#ed7953"
              ],
              [
                0.7777777777777778,
                "#fb9f3a"
              ],
              [
                0.8888888888888888,
                "#fdca26"
              ],
              [
                1.0,
                "#f0f921"
              ]
            ],
            "type": "heatmap"
          }
        ],
        "heatmapgl": [
          {
            "colorbar": {
              "outlinewidth": 0,
              "ticks": ""
            },
            "colorscale": [
              [
                0.0,
                "#0d0887"
              ],
              [
                0.1111111111111111,
                "#46039f"
              ],
              [
                0.2222222222222222,
                "#7201a8"
              ],
              [
                0.3333333333333333,
                "#9c179e"
              ],
              [
                0.4444444444444444,
                "#bd3786"
              ],
              [
                0.5555555555555556,
                "#d8576b"
              ],
              [
                0.6666666666666666,
                "#ed7953"
              ],
              [
                0.7777777777777778,
                "#fb9f3a"
              ],
              [
                0.8888888888888888,
                "#fdca26"
              ],
              [
                1.0,
                "#f0f921"
              ]
            ],
            "type": "heatmapgl"
          }
        ],
        "histogram": [
          {
            "marker": {
              "pattern": {
                "fillmode": "overlay",
                "size": 10,
                "solidity": 0.2
              }
            },
            "type": "histogram"
          }
        ],
        "histogram2d": [
          {
            "colorbar": {
              "outlinewidth": 0,
              "ticks": ""
            },
            "colorscale": [
              [
                0.0,
                "#0d0887"
              ],
              [
                0.1111111111111111,
                "#46039f"
              ],
              [
                0.2222222222222222,
                "#7201a8"
              ],
              [
                0.3333333333333333,
                "#9c179e"
              ],
              [
                0.4444444444444444,
                "#bd3786"
              ],
              [
                0.5555555555555556,
                "#d8576b"
              ],
              [
                0.6666666666666666,
                "#ed7953"
              ],
              [
                0.7777777777777778,
                "#fb9f3a"
              ],
              [
                0.8888888888888888,
                "#fdca26"
              ],
              [
                1.0,
                "#f0f921"
              ]
            ],
            "type": "histogram2d"
          }
        ],
        "histogram2dcontour": [
          {
            "colorbar": {
              "outlinewidth": 0,
              "ticks": ""
            },
            "colorscale": [
              [
                0.0,
                "#0d0887"
              ],
              [
                0.1111111111111111,
                "#46039f"
              ],
              [
                0.2222222222222222,
                "#7201a8"
              ],
              [
                0.3333333333333333,
                "#9c179e"
              ],
              [
                0.4444444444444444,
                "#bd3786"
              ],
              [
                0.5555555555555556,
                "#d8576b"
              ],
              [
                0.6666666666666666,
                "#ed7953"
              ],
              [
                0.7777777777777778,
                "#fb9f3a"
              ],
              [
                0.8888888888888888,
                "#fdca26"
              ],
              [
                1.0,
                "#f0f921"
              ]
            ],
            "type": "histogram2dcontour"
          }
        ],
        "mesh3d": [
          {
            "colorbar": {
              "outlinewidth": 0,
              "ticks": ""
            },
            "type": "mesh3d"
          }
        ],
        "parcoords": [
          {
            "line": {
              "colorbar": {
                "outlinewidth": 0,
                "ticks": ""
              }
            },
            "type": "parcoords"
          }
        ],
        "pie": [
          {
            "automargin": true,
            "type": "pie"
          }
        ],
        "scatter": [
          {
            "fillpattern": {
              "fillmode": "overlay",
              "size": 10,
              "solidity": 0.2
            },
            "type": "scatter"
          }
        ],
        "scatter3d": [
          {
            "line": {
              "colorbar": {
                "outlinewidth": 0,
                "ticks": ""
              }
            },
            "marker": {
              "colorbar": {
                "outlinewidth": 0,
                "ticks": ""
              }
            },
            "type": "scatter3d"
          }
        ],
        "scattercarpet": [
          {
            "marker": {
              "colorbar": {
                "outlinewidth": 0,
                "ticks": ""
              }
            },
            "type": "scattercarpet"
          }
        ],
        "scattergeo": [
          {
            "marker": {
              "colorbar": {
                "outlinewidth": 0,
                "ticks": ""
              }
            },
            "type": "scattergeo"
          }
        ],
        "scattergl": [
          {
            "marker": {
              "colorbar": {
                "outlinewidth": 0,
                "ticks": ""
              }
            },
            "type": "scattergl"
          }
        ],
        "scattermapbox": [
          {
            "marker": {
              "colorbar": {
                "outlinewidth": 0,
                "ticks": ""
              }
            },
            "type": "scattermapbox"
          }
        ],
        "scatterpolar": [
          {
            "marker": {
              "colorbar": {
                "outlinewidth": 0,
                "ticks": ""
              }
            },
            "type": "scatterpolar"
          }
        ],
        "scatterpolargl": [
          {
            "marker": {
              "colorbar": {
                "outlinewidth": 0,
                "ticks": ""
              }
            },
            "type": "scatterpolargl"
          }
        ],
        "scatterternary": [
          {
            "marker": {
              "colorbar": {
                "outlinewidth": 0,
                "ticks": ""
              }
            },
            "type": "scatterternary"
          }
        ],
        "surface": [
          {
            "colorbar": {
              "outlinewidth": 0,
              "ticks": ""
            },
            "colorscale": [
              [
                0.0,
                "#0d0887"
              ],
              [
                0.1111111111111111,
                "#46039f"
              ],
              [
                0.2222222222222222,
                "#7201a8"
              ],
              [
                0.3333333333333333,
                "#9c179e"
              ],
              [
                0.4444444444444444,
                "#bd3786"
              ],
              [
                0.5555555555555556,
                "#d8576b"
              ],
              [
                0.6666666666666666,
                "#ed7953"
              ],
              [
                0.7777777777777778,
                "#fb9f3a"
              ],
              [
                0.8888888888888888,
                "#fdca26"
              ],
              [
                1.0,
                "#f0f921"
              ]
            ],
            "type": "surface"
          }
        ],
        "table": [
          {
            "cells": {
              "fill": {
                "color": "#EBF0F8"
              },
              "line": {
                "color": "white"
              }
            },
            "header": {
              "fill": {
                "color": "#C8D4E3"
              },
              "line": {
                "color": "white"
              }
            },
            "type": "table"
          }
        ]
      },
      "layout": {
        "annotationdefaults": {
          "arrowcolor": "#2a3f5f",
          "arrowhead": 0,
          "arrowwidth": 1
        },
        "autotypenumbers": "strict",
        "coloraxis": {
          "colorbar": {
            "outlinewidth": 0,
            "ticks": ""
          }
        },
        "colorscale": {
          "diverging": [
            [
              0,
              "#8e0152"
            ],
            [
              0.1,
              "#c51b7d"
            ],
            [
              0.2,
              "#de77ae"
            ],
            [
              0.3,
              "#f1b6da"
            ],
            [
              0.4,
              "#fde0ef"
            ],
            [
              0.5,
              "#f7f7f7"
            ],
            [
              0.6,
              "#e6f5d0"
            ],
            [
              0.7,
              "#b8e186"
            ],
            [
              0.8,
              "#7fbc41"
            ],
            [
              0.9,
              "#4d9221"
            ],
            [
              1,
              "#276419"
            ]
          ],
          "sequential": [
            [
              0.0,
              "#0d0887"
            ],
            [
              0.1111111111111111,
              "#46039f"
            ],
            [
              0.2222222222222222,
              "#7201a8"
            ],
            [
              0.3333333333333333,
              "#9c179e"
            ],
            [
              0.4444444444444444,
              "#bd3786"
            ],
            [
              0.5555555555555556,
              "#d8576b"
            ],
            [
              0.6666666666666666,
              "#ed7953"
            ],
            [
              0.7777777777777778,
              "#fb9f3a"
            ],
            [
              0.8888888888888888,
              "#fdca26"
            ],
            [
              1.0,
              "#f0f921"
            ]
          ],
          "sequentialminus": [
            [
              0.0,
              "#0d0887"
            ],
            [
              0.1111111111111111,
              "#46039f"
            ],
            [
              0.2222222222222222,
              "#7201a8"
            ],
            [
              0.3333333333333333,
              "#9c179e"
            ],
            [
              0.4444444444444444,
              "#bd3786"
            ],
            [
              0.5555555555555556,
              "#d8576b"
            ],
            [
              0.6666666666666666,
              "#ed7953"
            ],
            [
              0.7777777777777778,
              "#fb9f3a"
            ],
            [
              0.8888888888888888,
              "#fdca26"
            ],
            [
              1.0,
              "#f0f921"
            ]
          ]
        },
        "colorway": [
          "#636efa",
          "#EF553B",
          "#00cc96",
          "#ab63fa",
          "#FFA15A",
          "#19d3f3",
          "#FF6692",
          "#B6E880",
          "#FF97FF",
          "#FECB52"
        ],
        "font": {
          "color": "#2a3f5f"
        },
        "geo": {
          "bgcolor": "white",
          "lakecolor": "white",
          "landcolor": "white",
          "showlakes": true,
          "showland": true,
          "subunitcolor": "#C8D4E3"
        },
        "hoverlabel": {
          "align": "left"
        },
        "hovermode": "closest",
        "mapbox": {
          "style": "light"
        },
        "paper_bgcolor": "white",
        "plot_bgcolor": "white",
        "polar": {
          "angularaxis": {
            "gridcolor": "#EBF0F8",
            "linecolor": "#EBF0F8",
            "ticks": ""
          },
          "bgcolor": "white",
          "radialaxis": {
            "gridcolor": "#EBF0F8",
            "linecolor": "#EBF0F8",
            "ticks": ""
          }
        },
        "scene": {
          "xaxis": {
            "backgroundcolor": "white",
            "gridcolor": "#DFE8F3",
            "gridwidth": 2,
            "linecolor": "#EBF0F8",
            "showbackground": true,
            "ticks": "",
            "zerolinecolor": "#EBF0F8"
          },
          "yaxis": {
            "backgroundcolor": "white",
            "gridcolor": "#DFE8F3",
            "gridwidth": 2,
            "linecolor": "#EBF0F8",
            "showbackground": true,
            "ticks": "",
            "zerolinecolor": "#EBF0F8"
          },
          "zaxis": {
            "backgroundcolor": "white",
            "gridcolor": "#DFE8F3",
            "gridwidth": 2,
            "linecolor": "#EBF0F8",
            "showbackground": true,
            "ticks": "",
            "zerolinecolor": "#EBF0F8"
          }
        },
        "shapedefaults": {
          "line": {
            "color": "#2a3f5f"
          }
        },
        "ternary": {
          "aaxis": {
            "gridcolor": "#DFE8F3",
            "linecolor": "#A2B1C6",
            "ticks": ""
          },
          "baxis": {
            "gridcolor": "#DFE8F3",
            "linecolor": "#A2B1C6",
            "ticks": ""
          },
          "bgcolor": "white",
          "caxis": {
            "gridcolor": "#DFE8F3",
            "linecolor": "#A2B1C6",
            "ticks": ""
          }
        },
        "title": {
          "x": 0.05
        },
        "xaxis": {
          "automargin": true,
          "gridcolor": "#EBF0F8",
          "linecolor": "#EBF0F8",
          "ticks": "",
          "title": {
            "standoff": 15
          },
          "zerolinecolor": "#EBF0F8",
          "zerolinewidth": 2
        },
        "yaxis": {
          "automargin": true,
          "gridcolor": "#EBF0F8",
          "linecolor": "#EBF0F8",
          "ticks": "",
          "title": {
            "standoff": 15
          },
          "zerolinecolor": "#EBF0F8",
          "zerolinewidth": 2
        }
      }
    },
    "width": 800,
    "xaxis": {
      "showgrid": false,
      "visible": false,
      "zeroline": false
    },
    "yaxis": {
      "scaleanchor": "x",
      "scaleratio": 1,
      "showgrid": false,
      "visible": false,
      "zeroline": false
    }
  }
}